{
  "platform": "apple",
  "country": "de",
  "genre": "Government",
  "genre_id": "1511",
  "slug": "government",
  "fetched_at": "2026-06-23T09:19:11Z",
  "count": 200,
  "shows": [
    {
      "rank": 1,
      "apple_id": "1592344037",
      "name": "Aus Politik und Zeitgeschichte (APuZ)",
      "artist": "bpb",
      "artwork": "https://is1-ssl.mzstatic.com/image/thumb/Podcasts116/v4/ac/4d/cd/ac4dcd01-dab2-3358-ce1b-75c8da2c1f8a/mza_10423090413538156762.png/170x170bb.png",
      "genre": "Government",
      "genre_id": "1511",
      "url": "https://podcasts.apple.com/de/podcast/aus-politik-und-zeitgeschichte-apuz/id1592344037?uo=2"
    },
    {
      "rank": 2,
      "apple_id": "1896778957",
      "name": "Hörvermerk – Der Wissenspodcast für Bundesbeschäftigte",
      "artist": "Bundesakademie für öffentliche Verwaltung im Bundesministerium des Innern",
      "artwork": "https://is1-ssl.mzstatic.com/image/thumb/Podcasts221/v4/df/67/8b/df678bca-2502-8747-69cf-ad6ae6d943fa/mza_15618764523914969462.jpg/170x170bb.png",
      "genre": "Government",
      "genre_id": "1511",
      "url": "https://podcasts.apple.com/de/podcast/h%C3%B6rvermerk-der-wissenspodcast-f%C3%BCr-bundesbesch%C3%A4ftigte/id1896778957?uo=2"
    },
    {
      "rank": 3,
      "apple_id": "1619334956",
      "name": "Nachgefragt: Krise, Krieg und Konflikte",
      "artist": "Redaktion Bundeswehr",
      "artwork": "https://is1-ssl.mzstatic.com/image/thumb/Podcasts122/v4/02/16/14/0216142f-027b-4529-2e24-727ccecafeb9/mza_16176189426752069515.jpg/170x170bb.png",
      "genre": "Government",
      "genre_id": "1511",
      "url": "https://podcasts.apple.com/de/podcast/nachgefragt-krise-krieg-und-konflikte/id1619334956?uo=2"
    },
    {
      "rank": 4,
      "apple_id": "1582443509",
      "name": "apolut: Tagesdosis",
      "artist": "apolut",
      "artwork": "https://is1-ssl.mzstatic.com/image/thumb/Podcasts115/v4/e8/bc/fa/e8bcfa7d-f108-5f7f-fdd3-423aff41d7b6/mza_8991001324927726388.jpeg/170x170bb.png",
      "genre": "Government",
      "genre_id": "1511",
      "url": "https://podcasts.apple.com/de/podcast/apolut-tagesdosis/id1582443509?uo=2"
    },
    {
      "rank": 5,
      "apple_id": "940596219",
      "name": "eGovernment Podcast",
      "artist": "Torsten Frenzel",
      "artwork": "https://is1-ssl.mzstatic.com/image/thumb/Podcasts116/v4/97/10/de/9710dedf-e8b6-4c07-9720-eb66ed438937/mza_9287126738065634600.png/170x170bb.png",
      "genre": "Government",
      "genre_id": "1511",
      "url": "https://podcasts.apple.com/de/podcast/egovernment-podcast/id940596219?uo=2"
    },
    {
      "rank": 6,
      "apple_id": "1437383375",
      "name": "Podcast vom Posten - Außenpolitik auf die Ohren!",
      "artist": "Auswärtiges Amt",
      "artwork": "https://is1-ssl.mzstatic.com/image/thumb/Podcasts211/v4/06/2d/42/062d42d1-d463-1132-8b47-88c04b6389d5/mza_8682208949160110962.jpg/170x170bb.png",
      "genre": "Government",
      "genre_id": "1511",
      "url": "https://podcasts.apple.com/de/podcast/podcast-vom-posten-au%C3%9Fenpolitik-auf-die-ohren/id1437383375?uo=2"
    },
    {
      "rank": 7,
      "apple_id": "1792409765",
      "name": "Job Secret - Der offizielle BND-Podcast",
      "artist": "Bundesnachrichtendienst (BND)",
      "artwork": "https://is1-ssl.mzstatic.com/image/thumb/Podcasts221/v4/93/38/84/933884c0-f554-3d52-1758-e37cf1b889eb/mza_9321375963935329136.jpg/170x170bb.png",
      "genre": "Government",
      "genre_id": "1511",
      "url": "https://podcasts.apple.com/de/podcast/job-secret-der-offizielle-bnd-podcast/id1792409765?uo=2"
    },
    {
      "rank": 8,
      "apple_id": "1488886120",
      "name": "Funkkreis: Podcast der Bundeswehr",
      "artist": "Redaktion der Bundeswehr",
      "artwork": "https://is1-ssl.mzstatic.com/image/thumb/Podcasts125/v4/5e/b3/8d/5eb38d88-6152-3c3f-31b3-27574f3c4c0a/mza_14048621856224217255.jpg/170x170bb.png",
      "genre": "Government",
      "genre_id": "1511",
      "url": "https://podcasts.apple.com/de/podcast/funkkreis-podcast-der-bundeswehr/id1488886120?uo=2"
    },
    {
      "rank": 9,
      "apple_id": "1534780078",
      "name": "Fiasco",
      "artist": "Pushkin Industries",
      "artwork": "https://is1-ssl.mzstatic.com/image/thumb/Podcasts221/v4/1e/f1/5d/1ef15d67-0ffc-3b14-61c0-b38523a13a29/mza_18225791986473524457.jpg/170x170bb.png",
      "genre": "Government",
      "genre_id": "1511",
      "url": "https://podcasts.apple.com/de/podcast/fiasco/id1534780078?uo=2"
    },
    {
      "rank": 10,
      "apple_id": "1512758742",
      "name": "Atlantic Talk Podcast",
      "artist": "Deutsche Atlantische Gesellschaft e.V.",
      "artwork": "https://is1-ssl.mzstatic.com/image/thumb/Podcasts116/v4/2c/d1/09/2cd10942-37b1-55fd-c7b3-4d389df81801/mza_8651910831323386324.png/170x170bb.png",
      "genre": "Government",
      "genre_id": "1511",
      "url": "https://podcasts.apple.com/de/podcast/atlantic-talk-podcast/id1512758742?uo=2"
    },
    {
      "rank": 11,
      "apple_id": "494517111",
      "name": "The Interview",
      "artist": "BBC World Service",
      "artwork": "https://is1-ssl.mzstatic.com/image/thumb/Podcasts221/v4/25/1e/73/251e73b6-0d64-c52b-945d-e5e22cf447d3/mza_5883862182275500832.jpg/170x170bb.png",
      "genre": "Government",
      "genre_id": "1511",
      "url": "https://podcasts.apple.com/de/podcast/the-interview/id494517111?uo=2"
    },
    {
      "rank": 12,
      "apple_id": "1670831449",
      "name": "Ludwigshafen, schon gehört?",
      "artist": "Stadtverwaltung Ludwigshafen am Rhein",
      "artwork": "https://is1-ssl.mzstatic.com/image/thumb/Podcasts126/v4/47/69/37/47693787-c48d-32c9-3715-2987d63359d5/mza_16921346971661387698.jpg/170x170bb.png",
      "genre": "Government",
      "genre_id": "1511",
      "url": "https://podcasts.apple.com/de/podcast/ludwigshafen-schon-geh%C3%B6rt/id1670831449?uo=2"
    },
    {
      "rank": 13,
      "apple_id": "1625265971",
      "name": "Die Jagd - Die geheimen Chats der AfD-Bundestagsfraktion",
      "artist": "WDR 5",
      "artwork": "https://is1-ssl.mzstatic.com/image/thumb/Podcasts122/v4/cc/f5/02/ccf502b3-e33b-a12c-5ef4-b448cdab1f3c/mza_16433614067866232521.jpg/170x170bb.png",
      "genre": "Government",
      "genre_id": "1511",
      "url": "https://podcasts.apple.com/de/podcast/die-jagd-die-geheimen-chats-der-afd-bundestagsfraktion/id1625265971?uo=2"
    },
    {
      "rank": 14,
      "apple_id": "1582444562",
      "name": "apolut: Standpunkte",
      "artist": "apolut",
      "artwork": "https://is1-ssl.mzstatic.com/image/thumb/Podcasts115/v4/45/b3/48/45b34840-6b56-51f9-5eea-32b537f74e45/mza_11619368931222072601.jpeg/170x170bb.png",
      "genre": "Government",
      "genre_id": "1511",
      "url": "https://podcasts.apple.com/de/podcast/apolut-standpunkte/id1582444562?uo=2"
    },
    {
      "rank": 15,
      "apple_id": "1295275185",
      "name": "POLITICO Money",
      "artist": "POLITICO",
      "artwork": "https://is1-ssl.mzstatic.com/image/thumb/Podcasts221/v4/c5/31/6a/c5316a7e-b938-4c13-cffd-14f236129a6a/mza_1670028661561525982.jpg/170x170bb.png",
      "genre": "Government",
      "genre_id": "1511",
      "url": "https://podcasts.apple.com/de/podcast/politico-money/id1295275185?uo=2"
    },
    {
      "rank": 16,
      "apple_id": "1525445350",
      "name": "Pekingology",
      "artist": "Center for Strategic and International Studies",
      "artwork": "https://is1-ssl.mzstatic.com/image/thumb/Podcasts211/v4/07/66/be/0766be71-95f5-c980-3040-7408c1760c9c/mza_15083037127963027902.jpg/170x170bb.png",
      "genre": "Government",
      "genre_id": "1511",
      "url": "https://podcasts.apple.com/de/podcast/pekingology/id1525445350?uo=2"
    },
    {
      "rank": 17,
      "apple_id": "1469168641",
      "name": "Strict Scrutiny",
      "artist": "Strict Scrutiny",
      "artwork": "https://is1-ssl.mzstatic.com/image/thumb/Podcasts221/v4/68/3f/62/683f6228-b15b-e0de-8c2c-e8c20860ca98/mza_763663699315012405.png/170x170bb.png",
      "genre": "Government",
      "genre_id": "1511",
      "url": "https://podcasts.apple.com/de/podcast/strict-scrutiny/id1469168641?uo=2"
    },
    {
      "rank": 18,
      "apple_id": "1896930920",
      "name": "KGSt-KommPakt",
      "artist": "Kommunale Gemeinschaftsstelle für Verwaltungsmanagement (KGSt)",
      "artwork": "https://is1-ssl.mzstatic.com/image/thumb/Podcasts211/v4/57/8c/8b/578c8bfd-38e0-f9e6-5e3b-2f99634ec082/mza_2603131575247582608.png/170x170bb.png",
      "genre": "Government",
      "genre_id": "1511",
      "url": "https://podcasts.apple.com/de/podcast/kgst-kommpakt/id1896930920?uo=2"
    },
    {
      "rank": 19,
      "apple_id": "1603801634",
      "name": "Welt der Geheimnisse",
      "artist": "Alexander Kluge",
      "artwork": "https://is1-ssl.mzstatic.com/image/thumb/Podcasts116/v4/26/35/ba/2635bac6-0920-42bf-4776-c477508cb059/mza_6090256823658489514.jpg/170x170bb.png",
      "genre": "Government",
      "genre_id": "1511",
      "url": "https://podcasts.apple.com/de/podcast/welt-der-geheimnisse/id1603801634?uo=2"
    },
    {
      "rank": 20,
      "apple_id": "1626113086",
      "name": "Im Krisenmodus",
      "artist": "Jan Jessen & Alexander Baumeister / Funke Mediengruppe",
      "artwork": "https://is1-ssl.mzstatic.com/image/thumb/Podcasts221/v4/84/c5/d6/84c5d699-b931-da75-1a4a-1f4de242b294/mza_4561991538778238415.jpg/170x170bb.png",
      "genre": "Government",
      "genre_id": "1511",
      "url": "https://podcasts.apple.com/de/podcast/im-krisenmodus/id1626113086?uo=2"
    },
    {
      "rank": 21,
      "apple_id": "1687260829",
      "name": "No es el fin del mundo",
      "artist": "El Orden Mundial",
      "artwork": "https://is1-ssl.mzstatic.com/image/thumb/Podcasts221/v4/f8/54/9c/f8549c63-c57c-3289-1368-b242ec5bf7b1/mza_17364458082571195587.jpg/170x170bb.png",
      "genre": "Government",
      "genre_id": "1511",
      "url": "https://podcasts.apple.com/de/podcast/no-es-el-fin-del-mundo/id1687260829?uo=2"
    },
    {
      "rank": 22,
      "apple_id": "1755570619",
      "name": "Die Akte Tulpenfeld. Ein Podcast der Bundesnetzagentur.",
      "artist": "Bundesnetzagentur für Elektrizität, Gas, Telekommunikation, Post und Eisenbahnen",
      "artwork": "https://is1-ssl.mzstatic.com/image/thumb/Podcasts221/v4/8f/67/51/8f6751b9-c531-dfb5-d35c-eaf6b20d109e/mza_16399741913834501379.jpg/170x170bb.png",
      "genre": "Government",
      "genre_id": "1511",
      "url": "https://podcasts.apple.com/de/podcast/die-akte-tulpenfeld-ein-podcast-der-bundesnetzagentur/id1755570619?uo=2"
    },
    {
      "rank": 23,
      "apple_id": "1440177480",
      "name": "KSK – Der Podcast zur Serie",
      "artist": "Bundeswehr Exclusive",
      "artwork": "https://is1-ssl.mzstatic.com/image/thumb/Podcasts211/v4/32/2e/43/322e43c7-874c-e558-d010-ac0999f53b85/mza_16344767554460993459.jpg/170x170bb.png",
      "genre": "Government",
      "genre_id": "1511",
      "url": "https://podcasts.apple.com/de/podcast/ksk-der-podcast-zur-serie/id1440177480?uo=2"
    },
    {
      "rank": 24,
      "apple_id": "1877864563",
      "name": "The Playbook",
      "artist": "bpb",
      "artwork": "https://is1-ssl.mzstatic.com/image/thumb/Podcasts211/v4/28/a9/18/28a918a6-26e6-be3d-e988-6e91502b6075/mza_17791950619694067661.png/170x170bb.png",
      "genre": "Government",
      "genre_id": "1511",
      "url": "https://podcasts.apple.com/de/podcast/the-playbook/id1877864563?uo=2"
    },
    {
      "rank": 25,
      "apple_id": "1890552134",
      "name": "America, Actually with Astead Herndon",
      "artist": "Vox Media",
      "artwork": "https://is1-ssl.mzstatic.com/image/thumb/Podcasts221/v4/c2/d4/03/c2d403e8-bff3-cfed-9fe9-3822edd09b76/mza_11989017264826421840.png/170x170bb.png",
      "genre": "Government",
      "genre_id": "1511",
      "url": "https://podcasts.apple.com/de/podcast/america-actually-with-astead-herndon/id1890552134?uo=2"
    },
    {
      "rank": 26,
      "apple_id": "1838747212",
      "name": "Cache Me If You Can",
      "artist": "Center for Strategic and International Studies",
      "artwork": "https://is1-ssl.mzstatic.com/image/thumb/Podcasts221/v4/5b/da/5f/5bda5f27-5635-fdcb-c93c-4f098484849d/mza_443062240444040561.jpeg/170x170bb.png",
      "genre": "Government",
      "genre_id": "1511",
      "url": "https://podcasts.apple.com/de/podcast/cache-me-if-you-can/id1838747212?uo=2"
    },
    {
      "rank": 27,
      "apple_id": "1802625282",
      "name": "Optimist Economy",
      "artist": "Kathryn Anne Edwards and Robin Rauzi",
      "artwork": "https://is1-ssl.mzstatic.com/image/thumb/Podcasts211/v4/51/fd/a5/51fda517-b295-8224-fdb4-f6a49ce2f56f/mza_17810033521087287533.png/170x170bb.png",
      "genre": "Government",
      "genre_id": "1511",
      "url": "https://podcasts.apple.com/de/podcast/optimist-economy/id1802625282?uo=2"
    },
    {
      "rank": 28,
      "apple_id": "1475699244",
      "name": "Our Curious Amalgam",
      "artist": "American Bar Association",
      "artwork": "https://is1-ssl.mzstatic.com/image/thumb/Podcasts123/v4/ca/26/64/ca2664a3-8a82-6f52-db19-e78c7ce0ae73/mza_9082632843107164391.jpg/170x170bb.png",
      "genre": "Government",
      "genre_id": "1511",
      "url": "https://podcasts.apple.com/de/podcast/our-curious-amalgam/id1475699244?uo=2"
    },
    {
      "rank": 29,
      "apple_id": "1782888887",
      "name": "Luis Elizondo - UAP Disclosure Updates",
      "artist": "Luis Elizondo",
      "artwork": "https://is1-ssl.mzstatic.com/image/thumb/Podcasts211/v4/75/b7/db/75b7dbdc-763a-49d4-4383-b1f7cde31455/mza_3097629094396328932.jpeg/170x170bb.png",
      "genre": "Government",
      "genre_id": "1511",
      "url": "https://podcasts.apple.com/de/podcast/luis-elizondo-uap-disclosure-updates/id1782888887?uo=2"
    },
    {
      "rank": 30,
      "apple_id": "1441573078",
      "name": "Into Africa",
      "artist": "CSIS  |  Center for Strategic and International Studies",
      "artwork": "https://is1-ssl.mzstatic.com/image/thumb/Podcasts211/v4/2d/26/3b/2d263bd3-95e5-3545-ef97-5a2d322544f3/mza_6476563487921874446.jpg/170x170bb.png",
      "genre": "Government",
      "genre_id": "1511",
      "url": "https://podcasts.apple.com/de/podcast/into-africa/id1441573078?uo=2"
    },
    {
      "rank": 31,
      "apple_id": "1576104593",
      "name": "HART AN DER GRENZE",
      "artist": "Kölner Flüchtlingsrat e.V.",
      "artwork": "https://is1-ssl.mzstatic.com/image/thumb/Podcasts116/v4/79/62/88/7962880e-93e4-e829-c544-2af97efebaec/mza_8809803638205306327.jpg/170x170bb.png",
      "genre": "Government",
      "genre_id": "1511",
      "url": "https://podcasts.apple.com/de/podcast/hart-an-der-grenze/id1576104593?uo=2"
    },
    {
      "rank": 32,
      "apple_id": "1779696367",
      "name": "USA",
      "artist": "Alexander Kluge",
      "artwork": "https://is1-ssl.mzstatic.com/image/thumb/Podcasts221/v4/9b/90/09/9b9009e2-99ef-08ba-884d-807d6be208fb/mza_115922292125442585.jpg/170x170bb.png",
      "genre": "Government",
      "genre_id": "1511",
      "url": "https://podcasts.apple.com/de/podcast/usa/id1779696367?uo=2"
    },
    {
      "rank": 33,
      "apple_id": "1659859439",
      "name": "DGPTalk: Z drugiej STRONY",
      "artist": "Dziennik Gazeta Prawna",
      "artwork": "https://is1-ssl.mzstatic.com/image/thumb/Podcasts126/v4/54/47/4c/54474c01-bebe-0312-8df8-83e5becca7d0/mza_1271775581189003282.jpeg/170x170bb.png",
      "genre": "Government",
      "genre_id": "1511",
      "url": "https://podcasts.apple.com/de/podcast/dgptalk-z-drugiej-strony/id1659859439?uo=2"
    },
    {
      "rank": 34,
      "apple_id": "1639346044",
      "name": "Grundrechte auf der Tonspur",
      "artist": "Emanuel V. Towfigh",
      "artwork": "https://is1-ssl.mzstatic.com/image/thumb/Podcasts112/v4/60/5c/5d/605c5dd2-0e7e-b855-0b6a-c2ce6068d1b6/mza_12085354073095161798.jpg/170x170bb.png",
      "genre": "Government",
      "genre_id": "1511",
      "url": "https://podcasts.apple.com/de/podcast/grundrechte-auf-der-tonspur/id1639346044?uo=2"
    },
    {
      "rank": 35,
      "apple_id": "1766500441",
      "name": "Lost im Bundestag",
      "artist": "ARD Hauptstadtstudio",
      "artwork": "https://is1-ssl.mzstatic.com/image/thumb/Podcasts221/v4/7f/0e/21/7f0e2144-fdff-3038-6d6a-e94ffcd923d1/mza_7883601140265472215.png/170x170bb.png",
      "genre": "Government",
      "genre_id": "1511",
      "url": "https://podcasts.apple.com/de/podcast/lost-im-bundestag/id1766500441?uo=2"
    },
    {
      "rank": 36,
      "apple_id": "1326698855",
      "name": "Capitalisn't",
      "artist": "University of Chicago Podcast Network",
      "artwork": "https://is1-ssl.mzstatic.com/image/thumb/Podcasts221/v4/b8/8a/ec/b88aec71-819d-28ea-22d3-05bd7f64eecf/mza_14244943143049554959.jpg/170x170bb.png",
      "genre": "Government",
      "genre_id": "1511",
      "url": "https://podcasts.apple.com/de/podcast/capitalisnt/id1326698855?uo=2"
    },
    {
      "rank": 37,
      "apple_id": "1514636385",
      "name": "Irregular Warfare Podcast",
      "artist": "Irregular Warfare Initiative",
      "artwork": "https://is1-ssl.mzstatic.com/image/thumb/Podcasts113/v4/ee/c4/c9/eec4c957-0a5e-d9fb-84aa-f6e10b73d153/mza_15001407860319352989.jpg/170x170bb.png",
      "genre": "Government",
      "genre_id": "1511",
      "url": "https://podcasts.apple.com/de/podcast/irregular-warfare-podcast/id1514636385?uo=2"
    },
    {
      "rank": 38,
      "apple_id": "1542346813",
      "name": "Экономика на слух",
      "artist": "РЭШ",
      "artwork": "https://is1-ssl.mzstatic.com/image/thumb/Podcasts112/v4/82/13/89/82138989-81d9-3393-8570-09c91c4eb0b5/mza_9978797168250851052.jpg/170x170bb.png",
      "genre": "Government",
      "genre_id": "1511",
      "url": "https://podcasts.apple.com/de/podcast/%D1%8D%D0%BA%D0%BE%D0%BD%D0%BE%D0%BC%D0%B8%D0%BA%D0%B0-%D0%BD%D0%B0-%D1%81%D0%BB%D1%83%D1%85/id1542346813?uo=2"
    },
    {
      "rank": 39,
      "apple_id": "1245002955",
      "name": "The DSR Network",
      "artist": "The DSR Network",
      "artwork": "https://is1-ssl.mzstatic.com/image/thumb/Podcasts211/v4/5e/5a/60/5e5a60eb-ff3d-16fd-b289-d7d2fcbcf8aa/mza_6618658443895976046.jpeg/170x170bb.png",
      "genre": "Government",
      "genre_id": "1511",
      "url": "https://podcasts.apple.com/de/podcast/the-dsr-network/id1245002955?uo=2"
    },
    {
      "rank": 40,
      "apple_id": "1848084976",
      "name": "NETZtalk. Ein Podcast der Bundesnetzagentur.",
      "artist": "Bundesnetzagentur",
      "artwork": "https://is1-ssl.mzstatic.com/image/thumb/Podcasts221/v4/7a/fc/74/7afc74a7-1519-69e7-ca30-31b0b381a828/mza_15368509832471867412.jpg/170x170bb.png",
      "genre": "Government",
      "genre_id": "1511",
      "url": "https://podcasts.apple.com/de/podcast/netztalk-ein-podcast-der-bundesnetzagentur/id1848084976?uo=2"
    },
    {
      "rank": 41,
      "apple_id": "1711240452",
      "name": "NatSec Matters",
      "artist": "Beacon Global Strategies LLC",
      "artwork": "https://is1-ssl.mzstatic.com/image/thumb/Podcasts221/v4/1b/c0/85/1bc085c6-6ca4-3a62-893d-41f55979b899/mza_6057310541017973266.jpg/170x170bb.png",
      "genre": "Government",
      "genre_id": "1511",
      "url": "https://podcasts.apple.com/de/podcast/natsec-matters/id1711240452?uo=2"
    },
    {
      "rank": 42,
      "apple_id": "1813094117",
      "name": "Leipzig & Leute – Der Podcast mit dem Oberbürgermeister",
      "artist": "Stadt Leipzig",
      "artwork": "https://is1-ssl.mzstatic.com/image/thumb/Podcasts211/v4/a9/b7/c7/a9b7c7b9-9fd1-2792-1514-60d00c28f0e4/mza_15293058201935011249.jpg/170x170bb.png",
      "genre": "Government",
      "genre_id": "1511",
      "url": "https://podcasts.apple.com/de/podcast/leipzig-leute-der-podcast-mit-dem-oberb%C3%BCrgermeister/id1813094117?uo=2"
    },
    {
      "rank": 43,
      "apple_id": "1652348242",
      "name": "UNBÜROKRATISCH",
      "artist": "eGovernment",
      "artwork": "https://is1-ssl.mzstatic.com/image/thumb/Podcasts211/v4/94/d4/dd/94d4dd64-8760-e582-8d4d-c5b3cd37a35a/mza_17189946943562037439.jpg/170x170bb.png",
      "genre": "Government",
      "genre_id": "1511",
      "url": "https://podcasts.apple.com/de/podcast/unb%C3%BCrokratisch/id1652348242?uo=2"
    },
    {
      "rank": 44,
      "apple_id": "1787264319",
      "name": "BorgenUdenFilter",
      "artist": "Lars Trier Mogensen, Henrik Qvortrup, Podads",
      "artwork": "https://is1-ssl.mzstatic.com/image/thumb/Podcasts221/v4/d1/13/ba/d113bae1-ab8d-f2b3-9173-87e635124a22/mza_13010965656832572287.jpg/170x170bb.png",
      "genre": "Government",
      "genre_id": "1511",
      "url": "https://podcasts.apple.com/de/podcast/borgenudenfilter/id1787264319?uo=2"
    },
    {
      "rank": 45,
      "apple_id": "1653768181",
      "name": "Irgendwas mit EU",
      "artist": "Europäisches Parlament, OH WOW",
      "artwork": "https://is1-ssl.mzstatic.com/image/thumb/Podcasts112/v4/c7/89/88/c78988b4-94d7-2dbb-4afb-f2ffdcf86213/mza_1433871840740936625.jpeg/170x170bb.png",
      "genre": "Government",
      "genre_id": "1511",
      "url": "https://podcasts.apple.com/de/podcast/irgendwas-mit-eu/id1653768181?uo=2"
    },
    {
      "rank": 46,
      "apple_id": "950410144",
      "name": "NATO Review",
      "artist": "Natochannel",
      "artwork": "https://is1-ssl.mzstatic.com/image/thumb/Podcasts126/v4/60/fb/77/60fb777c-c0bb-6d18-db90-b1aa108b954e/mza_12371839728873272713.jpg/170x170bb.png",
      "genre": "Government",
      "genre_id": "1511",
      "url": "https://podcasts.apple.com/de/podcast/nato-review/id950410144?uo=2"
    },
    {
      "rank": 47,
      "apple_id": "1453189561",
      "name": "EU trainee podcast",
      "artist": "EU Council",
      "artwork": "https://is1-ssl.mzstatic.com/image/thumb/Podcasts123/v4/64/2d/ce/642dce04-0aac-edb9-cbf4-6d851205611c/mza_5598392448398750198.jpg/170x170bb.png",
      "genre": "Government",
      "genre_id": "1511",
      "url": "https://podcasts.apple.com/de/podcast/eu-trainee-podcast/id1453189561?uo=2"
    },
    {
      "rank": 48,
      "apple_id": "1532736903",
      "name": "Prognosticky ústav",
      "artist": "Dominik Presl, Kryštof Míšek",
      "artwork": "https://is1-ssl.mzstatic.com/image/thumb/Podcasts115/v4/8a/af/29/8aaf2907-b1a2-620b-bb16-277f05ed4e76/mza_3840545256329097696.jpg/170x170bb.png",
      "genre": "Government",
      "genre_id": "1511",
      "url": "https://podcasts.apple.com/de/podcast/prognosticky-%C3%BAstav/id1532736903?uo=2"
    },
    {
      "rank": 49,
      "apple_id": "1445901378",
      "name": "Pitchfork Economics with Nick Hanauer",
      "artist": "Civic Ventures",
      "artwork": "https://is1-ssl.mzstatic.com/image/thumb/Podcasts221/v4/f5/7b/f2/f57bf2d7-9466-d4ad-1d6c-d388a3c020b5/mza_5870286279560073741.jpg/170x170bb.png",
      "genre": "Government",
      "genre_id": "1511",
      "url": "https://podcasts.apple.com/de/podcast/pitchfork-economics-with-nick-hanauer/id1445901378?uo=2"
    },
    {
      "rank": 50,
      "apple_id": "1559161492",
      "name": "Alles über Rechtliche Betreuung und Vorsorge",
      "artist": "Kathrin Kaiser und Ulrike Gödeke",
      "artwork": "https://is1-ssl.mzstatic.com/image/thumb/Podcasts211/v4/8a/ec/74/8aec74a3-6690-b620-5f95-1a76f33b87b6/mza_10868545698584939783.jpg/170x170bb.png",
      "genre": "Government",
      "genre_id": "1511",
      "url": "https://podcasts.apple.com/de/podcast/alles-%C3%BCber-rechtliche-betreuung-und-vorsorge/id1559161492?uo=2"
    },
    {
      "rank": 51,
      "apple_id": "1622204524",
      "name": "Sig det' løgn",
      "artist": "RADIO IIII",
      "artwork": "https://is1-ssl.mzstatic.com/image/thumb/Podcasts221/v4/21/c3/b8/21c3b80d-b52c-198b-96a2-e16a0ae53457/mza_12132603034291629400.jpg/170x170bb.png",
      "genre": "Government",
      "genre_id": "1511",
      "url": "https://podcasts.apple.com/de/podcast/sig-det-l%C3%B8gn/id1622204524?uo=2"
    },
    {
      "rank": 52,
      "apple_id": "1497785843",
      "name": "5-4",
      "artist": "Prologue Projects",
      "artwork": "https://is1-ssl.mzstatic.com/image/thumb/Podcasts114/v4/ca/d5/c1/cad5c11c-26c6-7e25-afc7-9a496c7f6e03/mza_5631414486129804049.jpeg/170x170bb.png",
      "genre": "Government",
      "genre_id": "1511",
      "url": "https://podcasts.apple.com/de/podcast/5-4/id1497785843?uo=2"
    },
    {
      "rank": 53,
      "apple_id": "1863389853",
      "name": "Zwischen Düne und Dienstweg",
      "artist": "Inselverwaltung Sylt",
      "artwork": "https://is1-ssl.mzstatic.com/image/thumb/Podcasts211/v4/2e/dc/4c/2edc4c83-5db2-b45b-d7c6-830c4e7abb44/mza_15195373216669063293.jpg/170x170bb.png",
      "genre": "Government",
      "genre_id": "1511",
      "url": "https://podcasts.apple.com/de/podcast/zwischen-d%C3%BCne-und-dienstweg/id1863389853?uo=2"
    },
    {
      "rank": 54,
      "apple_id": "1597496780",
      "name": "Fora do Baralho",
      "artist": "Rádio Observador",
      "artwork": "https://is1-ssl.mzstatic.com/image/thumb/Podcasts221/v4/4f/a9/f6/4fa9f624-53d0-0a44-7773-cf19450966f5/mza_16573071879318213401.jpg/170x170bb.png",
      "genre": "Government",
      "genre_id": "1511",
      "url": "https://podcasts.apple.com/de/podcast/fora-do-baralho/id1597496780?uo=2"
    },
    {
      "rank": 55,
      "apple_id": "1454636634",
      "name": "Encuentros Fundación Telefónica",
      "artist": "Fundación Telefónica",
      "artwork": "https://is1-ssl.mzstatic.com/image/thumb/Podcasts124/v4/a4/b3/01/a4b30159-8306-62a8-68fc-1e07996298e6/mza_1855111538284015354.jpg/170x170bb.png",
      "genre": "Government",
      "genre_id": "1511",
      "url": "https://podcasts.apple.com/de/podcast/encuentros-fundaci%C3%B3n-telef%C3%B3nica/id1454636634?uo=2"
    },
    {
      "rank": 56,
      "apple_id": "1887157889",
      "name": "プチ鹿島 赤坂タイムス",
      "artist": "TBS RADIO",
      "artwork": "https://is1-ssl.mzstatic.com/image/thumb/Podcasts221/v4/6d/7a/e4/6d7ae453-095d-9668-ab5a-a073d649adba/mza_9989597748288121912.jpg/170x170bb.png",
      "genre": "Government",
      "genre_id": "1511",
      "url": "https://podcasts.apple.com/de/podcast/%E3%83%97%E3%83%81%E9%B9%BF%E5%B3%B6-%E8%B5%A4%E5%9D%82%E3%82%BF%E3%82%A4%E3%83%A0%E3%82%B9/id1887157889?uo=2"
    },
    {
      "rank": 57,
      "apple_id": "1896239265",
      "name": "הבעיה של השמאל",
      "artist": "הבעיה של השמאל",
      "artwork": "https://is1-ssl.mzstatic.com/image/thumb/Podcasts211/v4/bb/53/66/bb53669a-e5b1-8114-a99e-ddd543104d4b/mza_16413812677134809698.jpg/170x170bb.png",
      "genre": "Government",
      "genre_id": "1511",
      "url": "https://podcasts.apple.com/de/podcast/%D7%94%D7%91%D7%A2%D7%99%D7%94-%D7%A9%D7%9C-%D7%94%D7%A9%D7%9E%D7%90%D7%9C/id1896239265?uo=2"
    },
    {
      "rank": 58,
      "apple_id": "444786081",
      "name": "Official Prime Minister's Questions (PMQs) Podcast",
      "artist": "UK Parliament",
      "artwork": "https://is1-ssl.mzstatic.com/image/thumb/Podcasts71/v4/2e/f1/98/2ef198e9-4a25-45b5-8efe-83afc8bb18e7/mza_8389723669653800488.jpg/170x170bb.png",
      "genre": "Government",
      "genre_id": "1511",
      "url": "https://podcasts.apple.com/de/podcast/official-prime-ministers-questions-pmqs-podcast/id444786081?uo=2"
    },
    {
      "rank": 59,
      "apple_id": "1596587030",
      "name": "STUDIO M - Der Podcast von MEMORIAL Deutschland",
      "artist": "MEMORIAL Deutschland",
      "artwork": "https://is1-ssl.mzstatic.com/image/thumb/Podcasts211/v4/a3/e7/62/a3e762f4-ef4f-6489-1627-ecd63a7416ad/mza_10877202580857087761.png/170x170bb.png",
      "genre": "Government",
      "genre_id": "1511",
      "url": "https://podcasts.apple.com/de/podcast/studio-m-der-podcast-von-memorial-deutschland/id1596587030?uo=2"
    },
    {
      "rank": 60,
      "apple_id": "1515123608",
      "name": "Gerhard Schröder - Die Agenda",
      "artist": "Béla Anda",
      "artwork": "https://is1-ssl.mzstatic.com/image/thumb/Podcasts115/v4/20/7b/13/207b13d1-d90e-afcf-aed6-c7f8ba34b8b6/mza_7830540047491909600.jpg/170x170bb.png",
      "genre": "Government",
      "genre_id": "1511",
      "url": "https://podcasts.apple.com/de/podcast/gerhard-schr%C3%B6der-die-agenda/id1515123608?uo=2"
    },
    {
      "rank": 61,
      "apple_id": "1748663426",
      "name": "Trash Talk... with Count Binface",
      "artist": "Biscuit Jim Creative",
      "artwork": "https://is1-ssl.mzstatic.com/image/thumb/Podcasts221/v4/db/45/84/db4584c0-0ac0-ffda-be06-4947622dab58/mza_3760419894304322741.jpeg/170x170bb.png",
      "genre": "Government",
      "genre_id": "1511",
      "url": "https://podcasts.apple.com/de/podcast/trash-talk-with-count-binface/id1748663426?uo=2"
    },
    {
      "rank": 62,
      "apple_id": "1663585179",
      "name": "Democracy in America - Alexis de Tocqueville",
      "artist": "Alexis de Tocqueville",
      "artwork": "https://is1-ssl.mzstatic.com/image/thumb/Podcasts221/v4/94/9e/c4/949ec417-6bd5-3c3b-aa7e-1997eeb2d8b0/mza_5537349238652809236.jpg/170x170bb.png",
      "genre": "Government",
      "genre_id": "1511",
      "url": "https://podcasts.apple.com/de/podcast/democracy-in-america-alexis-de-tocqueville/id1663585179?uo=2"
    },
    {
      "rank": 63,
      "apple_id": "1466788788",
      "name": "Funkdisziplin – der Bundespolizei-Podcast",
      "artist": "Bundespolizei",
      "artwork": "https://is1-ssl.mzstatic.com/image/thumb/Podcasts125/v4/88/66/98/886698f2-402e-da55-cb9d-16fa2e61d0bf/mza_16229972180908667776.jpg/170x170bb.png",
      "genre": "Government",
      "genre_id": "1511",
      "url": "https://podcasts.apple.com/de/podcast/funkdisziplin-der-bundespolizei-podcast/id1466788788?uo=2"
    },
    {
      "rank": 64,
      "apple_id": "1481185951",
      "name": "Tacheles Thüringen",
      "artist": "Fabian Klaus, Elmar Otto, Elena Vogel",
      "artwork": "https://is1-ssl.mzstatic.com/image/thumb/Podcasts221/v4/3e/29/0c/3e290ce2-04d3-76f5-0f87-fbff4d7fc3b2/mza_6798469205780054816.jpg/170x170bb.png",
      "genre": "Government",
      "genre_id": "1511",
      "url": "https://podcasts.apple.com/de/podcast/tacheles-th%C3%BCringen/id1481185951?uo=2"
    },
    {
      "rank": 65,
      "apple_id": "1564065871",
      "name": "Global Security Briefing",
      "artist": "The Royal United Services Institute",
      "artwork": "https://is1-ssl.mzstatic.com/image/thumb/Podcasts211/v4/37/8e/fe/378efee9-0be1-c5cf-b9fa-43f69b544fda/mza_2571466634186281743.png/170x170bb.png",
      "genre": "Government",
      "genre_id": "1511",
      "url": "https://podcasts.apple.com/de/podcast/global-security-briefing/id1564065871?uo=2"
    },
    {
      "rank": 66,
      "apple_id": "498897343",
      "name": "The Lawfare Podcast",
      "artist": "The Lawfare Institute",
      "artwork": "https://is1-ssl.mzstatic.com/image/thumb/Podcasts211/v4/fb/ff/d7/fbffd791-aa59-3dfe-56da-b5d5be4e0df9/mza_3314617112618523122.jpeg/170x170bb.png",
      "genre": "Government",
      "genre_id": "1511",
      "url": "https://podcasts.apple.com/de/podcast/the-lawfare-podcast/id498897343?uo=2"
    },
    {
      "rank": 67,
      "apple_id": "1695561409",
      "name": "Abgehört",
      "artist": "Bayerisches Landesamt für Verfassungsschutz",
      "artwork": "https://is1-ssl.mzstatic.com/image/thumb/Podcasts126/v4/72/6a/ea/726aea9f-12ce-cb96-e98c-76f892b0fb2d/mza_9490407703658849938.jpg/170x170bb.png",
      "genre": "Government",
      "genre_id": "1511",
      "url": "https://podcasts.apple.com/de/podcast/abgeh%C3%B6rt/id1695561409?uo=2"
    },
    {
      "rank": 68,
      "apple_id": "1390954299",
      "name": "The Military Leader",
      "artist": "The Military Leader",
      "artwork": "https://is1-ssl.mzstatic.com/image/thumb/Podcasts126/v4/3d/36/84/3d368448-8a9b-be90-d1ac-95d1cebbdce6/mza_9881980761634636608.jpeg/170x170bb.png",
      "genre": "Government",
      "genre_id": "1511",
      "url": "https://podcasts.apple.com/de/podcast/the-military-leader/id1390954299?uo=2"
    },
    {
      "rank": 69,
      "apple_id": "1561252894",
      "name": "From the Crows' Nest",
      "artist": "Association of Old Crows",
      "artwork": "https://is1-ssl.mzstatic.com/image/thumb/Podcasts211/v4/47/c3/41/47c34110-311a-ab79-74cb-957e225fc5dc/mza_10694763760877078152.jpg/170x170bb.png",
      "genre": "Government",
      "genre_id": "1511",
      "url": "https://podcasts.apple.com/de/podcast/from-the-crows-nest/id1561252894?uo=2"
    },
    {
      "rank": 70,
      "apple_id": "1641671307",
      "name": "Denkanstoß Demokratie",
      "artist": "Denkanstoß Demokratie",
      "artwork": "https://is1-ssl.mzstatic.com/image/thumb/Podcasts122/v4/08/fe/05/08fe050e-1db6-d7cf-3a14-e5e27079bbb0/mza_2893409989230917864.jpg/170x170bb.png",
      "genre": "Government",
      "genre_id": "1511",
      "url": "https://podcasts.apple.com/de/podcast/denkansto%C3%9F-demokratie/id1641671307?uo=2"
    },
    {
      "rank": 71,
      "apple_id": "1818389132",
      "name": "State of Play",
      "artist": "Center for Strategic and International Studies",
      "artwork": "https://is1-ssl.mzstatic.com/image/thumb/Podcasts211/v4/b7/e5/42/b7e542ae-2264-894b-0c23-17ce774835e6/mza_4920077590884006751.jpg/170x170bb.png",
      "genre": "Government",
      "genre_id": "1511",
      "url": "https://podcasts.apple.com/de/podcast/state-of-play/id1818389132?uo=2"
    },
    {
      "rank": 72,
      "apple_id": "1559865448",
      "name": "Space Strategy",
      "artist": "Space Pod",
      "artwork": "https://is1-ssl.mzstatic.com/image/thumb/Podcasts115/v4/13/9d/bc/139dbcf6-07b1-4599-2456-ea9ccb884c3e/mza_9000658717582288825.jpg/170x170bb.png",
      "genre": "Government",
      "genre_id": "1511",
      "url": "https://podcasts.apple.com/de/podcast/space-strategy/id1559865448?uo=2"
    },
    {
      "rank": 73,
      "apple_id": "1610093714",
      "name": "Was ist die EU?",
      "artist": "Hessische Landeszentrale für politische Bildung",
      "artwork": "https://is1-ssl.mzstatic.com/image/thumb/Podcasts126/v4/65/36/19/653619f7-5c36-feca-acbe-b9c6d535ad78/mza_11348332717901515782.png/170x170bb.png",
      "genre": "Government",
      "genre_id": "1511",
      "url": "https://podcasts.apple.com/de/podcast/was-ist-die-eu/id1610093714?uo=2"
    },
    {
      "rank": 74,
      "apple_id": "1325239734",
      "name": "Karriereberatungsbüro der Bundeswehr Schwerin",
      "artist": "Hauptmann Blüggel",
      "artwork": "https://is1-ssl.mzstatic.com/image/thumb/Podcasts125/v4/c0/c6/00/c0c6003c-ed9a-ee70-55ce-a6b70d9a6f3c/mza_13370133758566635912.jpg/170x170bb.png",
      "genre": "Government",
      "genre_id": "1511",
      "url": "https://podcasts.apple.com/de/podcast/karriereberatungsb%C3%BCro-der-bundeswehr-schwerin/id1325239734?uo=2"
    },
    {
      "rank": 75,
      "apple_id": "456568775",
      "name": "Any Questions? and Any Answers?",
      "artist": "BBC Radio 4",
      "artwork": "https://is1-ssl.mzstatic.com/image/thumb/Podcasts221/v4/b7/76/81/b776814f-6952-6ccd-ee60-66a6d80dfa8b/mza_3722279796151217078.jpg/170x170bb.png",
      "genre": "Government",
      "genre_id": "1511",
      "url": "https://podcasts.apple.com/de/podcast/any-questions-and-any-answers/id456568775?uo=2"
    },
    {
      "rank": 76,
      "apple_id": "1333127700",
      "name": "The Proceedings Podcast",
      "artist": "U.S. Naval Institute",
      "artwork": "https://is1-ssl.mzstatic.com/image/thumb/Podcasts123/v4/78/d7/43/78d74343-5981-5563-58a8-271fef3ab865/mza_6416196988301429167.jpg/170x170bb.png",
      "genre": "Government",
      "genre_id": "1511",
      "url": "https://podcasts.apple.com/de/podcast/the-proceedings-podcast/id1333127700?uo=2"
    },
    {
      "rank": 77,
      "apple_id": "1216235459",
      "name": "Royal Aeronautical Society Podcast",
      "artist": "AeroSociety Podcast",
      "artwork": "https://is1-ssl.mzstatic.com/image/thumb/Podcasts221/v4/e6/d6/2a/e6d62a5a-9c5b-1a27-7d2b-bd7af0b4b75d/mza_16387083359628396072.png/170x170bb.png",
      "genre": "Government",
      "genre_id": "1511",
      "url": "https://podcasts.apple.com/de/podcast/royal-aeronautical-society-podcast/id1216235459?uo=2"
    },
    {
      "rank": 78,
      "apple_id": "1896823188",
      "name": "USAREUR-AF News Brief",
      "artist": "U.S. Army Europe and Africa",
      "artwork": "https://is1-ssl.mzstatic.com/image/thumb/Podcasts221/v4/53/e3/32/53e3323d-a023-b339-39a0-b90431751127/mza_5856482163210155813.jpg/170x170bb.png",
      "genre": "Government",
      "genre_id": "1511",
      "url": "https://podcasts.apple.com/de/podcast/usareur-af-news-brief/id1896823188?uo=2"
    },
    {
      "rank": 79,
      "apple_id": "1254976698",
      "name": "enthusiastisch-leben-podcast Archive - Yoga Vidya Blog - Yoga, Meditation und Ayurveda",
      "artist": "Sukadev Bretz",
      "artwork": "https://is1-ssl.mzstatic.com/image/thumb/Podcasts123/v4/3f/2e/ae/3f2eae1e-90c3-547e-a8c5-7acf4ceb1103/mza_4608862551594936730.jpg/170x170bb.png",
      "genre": "Government",
      "genre_id": "1511",
      "url": "https://podcasts.apple.com/de/podcast/enthusiastisch-leben-podcast-archive-yoga-vidya-blog/id1254976698?uo=2"
    },
    {
      "rank": 80,
      "apple_id": "264518537",
      "name": "The Week in Westminster",
      "artist": "BBC Radio 4",
      "artwork": "https://is1-ssl.mzstatic.com/image/thumb/Podcasts211/v4/cd/f8/bd/cdf8bd0c-c924-51df-35af-43566753cc31/mza_18094194195936843160.jpg/170x170bb.png",
      "genre": "Government",
      "genre_id": "1511",
      "url": "https://podcasts.apple.com/de/podcast/the-week-in-westminster/id264518537?uo=2"
    },
    {
      "rank": 81,
      "apple_id": "1889690420",
      "name": "American Power",
      "artist": "Chad Scott, Nat Towsen, Mr. Global",
      "artwork": "https://is1-ssl.mzstatic.com/image/thumb/Podcasts221/v4/99/31/61/993161bf-bbcd-093f-7396-251b57fd319d/mza_17834578799442139327.jpg/170x170bb.png",
      "genre": "Government",
      "genre_id": "1511",
      "url": "https://podcasts.apple.com/de/podcast/american-power/id1889690420?uo=2"
    },
    {
      "rank": 82,
      "apple_id": "265307843",
      "name": "The Law Show",
      "artist": "BBC Radio 4",
      "artwork": "https://is1-ssl.mzstatic.com/image/thumb/Podcasts211/v4/a9/d9/b7/a9d9b7a7-f07b-8055-7461-8f0ec968454f/mza_12310003861209507349.jpg/170x170bb.png",
      "genre": "Government",
      "genre_id": "1511",
      "url": "https://podcasts.apple.com/de/podcast/the-law-show/id265307843?uo=2"
    },
    {
      "rank": 83,
      "apple_id": "1462879154",
      "name": "El Orden Mundial",
      "artist": "OndaCero",
      "artwork": "https://is1-ssl.mzstatic.com/image/thumb/Podcasts125/v4/e5/7c/ad/e57cad97-4c43-54e6-04d7-c42d843c60c8/mza_5598980088924673234.jpg/170x170bb.png",
      "genre": "Government",
      "genre_id": "1511",
      "url": "https://podcasts.apple.com/de/podcast/el-orden-mundial/id1462879154?uo=2"
    },
    {
      "rank": 84,
      "apple_id": "1585954195",
      "name": "Rheingehäckt",
      "artist": "Wolfgang Straßer/Fabian Haun",
      "artwork": "https://is1-ssl.mzstatic.com/image/thumb/Podcasts125/v4/cb/53/53/cb5353dc-bd02-68ec-dc5b-788bbc86d4e4/mza_17521889949860754270.png/170x170bb.png",
      "genre": "Government",
      "genre_id": "1511",
      "url": "https://podcasts.apple.com/de/podcast/rheingeh%C3%A4ckt/id1585954195?uo=2"
    },
    {
      "rank": 85,
      "apple_id": "1500013142",
      "name": "KenFM: Im Gespräch",
      "artist": "KenFM",
      "artwork": "https://is1-ssl.mzstatic.com/image/thumb/Podcasts125/v4/db/c8/6b/dbc86b16-9576-ce91-664b-b6c39b9ece92/mza_9749861426976829473.jpeg/170x170bb.png",
      "genre": "Government",
      "genre_id": "1511",
      "url": "https://podcasts.apple.com/de/podcast/kenfm-im-gespr%C3%A4ch/id1500013142?uo=2"
    },
    {
      "rank": 86,
      "apple_id": "369032477",
      "name": "The Strong Towns Podcast",
      "artist": "Strong Towns",
      "artwork": "https://is1-ssl.mzstatic.com/image/thumb/Podcasts122/v4/63/63/8c/63638c2a-3e02-dc38-8a26-50a832d39a6f/mza_868145100848425715.jpg/170x170bb.png",
      "genre": "Government",
      "genre_id": "1511",
      "url": "https://podcasts.apple.com/de/podcast/the-strong-towns-podcast/id369032477?uo=2"
    },
    {
      "rank": 87,
      "apple_id": "1829969009",
      "name": "سوريا.. لوين؟",
      "artist": "DW",
      "artwork": "https://is1-ssl.mzstatic.com/image/thumb/Podcasts221/v4/d3/2a/8d/d32a8d3e-9ccd-b46a-b857-3b7299070a55/mza_15046242983314457752.jpg/170x170bb.png",
      "genre": "Government",
      "genre_id": "1511",
      "url": "https://podcasts.apple.com/de/podcast/%D8%B3%D9%88%D8%B1%D9%8A%D8%A7-%D9%84%D9%88%D9%8A%D9%86/id1829969009?uo=2"
    },
    {
      "rank": 88,
      "apple_id": "1501964274",
      "name": "Macroaggressions",
      "artist": "Charlie Robinson",
      "artwork": "https://is1-ssl.mzstatic.com/image/thumb/Podcasts211/v4/a2/ec/bd/a2ecbded-22e0-7ea0-f6aa-7192268c4df5/mza_392695618488340579.jpg/170x170bb.png",
      "genre": "Government",
      "genre_id": "1511",
      "url": "https://podcasts.apple.com/de/podcast/macroaggressions/id1501964274?uo=2"
    },
    {
      "rank": 89,
      "apple_id": "1498955455",
      "name": "KenFM: Tagesdosis",
      "artist": "KenFM",
      "artwork": "https://is1-ssl.mzstatic.com/image/thumb/Podcasts125/v4/99/9b/7a/999b7a3d-9085-78d1-960f-1d162d35a09d/mza_15793452419382667427.jpeg/170x170bb.png",
      "genre": "Government",
      "genre_id": "1511",
      "url": "https://podcasts.apple.com/de/podcast/kenfm-tagesdosis/id1498955455?uo=2"
    },
    {
      "rank": 90,
      "apple_id": "1778429352",
      "name": "Wo bist Du? Verschollen auf der Flucht",
      "artist": "ARD",
      "artwork": "https://is1-ssl.mzstatic.com/image/thumb/Podcasts211/v4/bf/95/08/bf9508b9-00c2-3b63-6999-c2611544687e/mza_2723778782439369017.jpg/170x170bb.png",
      "genre": "Government",
      "genre_id": "1511",
      "url": "https://podcasts.apple.com/de/podcast/wo-bist-du-verschollen-auf-der-flucht/id1778429352?uo=2"
    },
    {
      "rank": 91,
      "apple_id": "421110541",
      "name": "Westminster Hour",
      "artist": "BBC Radio 4",
      "artwork": "https://is1-ssl.mzstatic.com/image/thumb/Podcasts211/v4/c0/76/b6/c076b6ed-594a-0525-9a43-deaad6339f0d/mza_15716301080334303178.jpg/170x170bb.png",
      "genre": "Government",
      "genre_id": "1511",
      "url": "https://podcasts.apple.com/de/podcast/westminster-hour/id421110541?uo=2"
    },
    {
      "rank": 92,
      "apple_id": "1811176978",
      "name": "The Tara Palmeri Show",
      "artist": "Tara Palmeri",
      "artwork": "https://is1-ssl.mzstatic.com/image/thumb/Podcasts221/v4/d2/d0/ef/d2d0eff0-f962-d68b-b460-4b1d6a23abee/mza_8512596653231893642.jpg/170x170bb.png",
      "genre": "Government",
      "genre_id": "1511",
      "url": "https://podcasts.apple.com/de/podcast/the-tara-palmeri-show/id1811176978?uo=2"
    },
    {
      "rank": 93,
      "apple_id": "1840860950",
      "name": "Irregular Warfare Podcast",
      "artist": "Irregular Warfare Initiative",
      "artwork": "https://is1-ssl.mzstatic.com/image/thumb/Podcasts211/v4/75/f1/2a/75f12a06-aeb6-1642-3327-1bfe866fe97e/mza_18276365138871007446.jpg/170x170bb.png",
      "genre": "Government",
      "genre_id": "1511",
      "url": "https://podcasts.apple.com/de/podcast/irregular-warfare-podcast/id1840860950?uo=2"
    },
    {
      "rank": 94,
      "apple_id": "1618827980",
      "name": "Последний Понедельник",
      "artist": "Совет по международным отношениям \"Минский диалог\"",
      "artwork": "https://is1-ssl.mzstatic.com/image/thumb/Podcasts221/v4/05/1c/4b/051c4b45-57d5-3a86-74cc-8fed81787134/mza_17223038664550107863.png/170x170bb.png",
      "genre": "Government",
      "genre_id": "1511",
      "url": "https://podcasts.apple.com/de/podcast/%D0%BF%D0%BE%D1%81%D0%BB%D0%B5%D0%B4%D0%BD%D0%B8%D0%B9-%D0%BF%D0%BE%D0%BD%D0%B5%D0%B4%D0%B5%D0%BB%D1%8C%D0%BD%D0%B8%D0%BA/id1618827980?uo=2"
    },
    {
      "rank": 95,
      "apple_id": "1711217011",
      "name": "Government's Future Frontiers",
      "artist": "Deloitte Insights",
      "artwork": "https://is1-ssl.mzstatic.com/image/thumb/Podcasts116/v4/01/b3/ab/01b3aba6-ccd4-3aa8-e3f6-742297050c98/mza_12259691002222923697.jpg/170x170bb.png",
      "genre": "Government",
      "genre_id": "1511",
      "url": "https://podcasts.apple.com/de/podcast/governments-future-frontiers/id1711217011?uo=2"
    },
    {
      "rank": 96,
      "apple_id": "1562613079",
      "name": "Xi Jinping’s China",
      "artist": "Amber Tinney",
      "artwork": "https://is1-ssl.mzstatic.com/image/thumb/Podcasts124/v4/6d/cd/b2/6dcdb20c-ce1e-bc7a-7979-1424b295c732/mza_15186249751479739864.jpg/170x170bb.png",
      "genre": "Government",
      "genre_id": "1511",
      "url": "https://podcasts.apple.com/de/podcast/xi-jinpings-china/id1562613079?uo=2"
    },
    {
      "rank": 97,
      "apple_id": "1554726317",
      "name": "Anja am Apparat - der Politikpodcast",
      "artist": "Anja Ingenbleek",
      "artwork": "https://is1-ssl.mzstatic.com/image/thumb/Podcasts114/v4/c7/cc/ae/c7ccaee9-64c7-58b7-c945-cf6c51a69ba7/mza_12769481014577321824.jpg/170x170bb.png",
      "genre": "Government",
      "genre_id": "1511",
      "url": "https://podcasts.apple.com/de/podcast/anja-am-apparat-der-politikpodcast/id1554726317?uo=2"
    },
    {
      "rank": 98,
      "apple_id": "1558608802",
      "name": "The Jedburgh Podcast",
      "artist": "Fran Racioppi",
      "artwork": "https://is1-ssl.mzstatic.com/image/thumb/Podcasts221/v4/de/a0/d4/dea0d434-5b3a-15fc-347a-4555881b811e/mza_11920592808349750539.jpeg/170x170bb.png",
      "genre": "Government",
      "genre_id": "1511",
      "url": "https://podcasts.apple.com/de/podcast/the-jedburgh-podcast/id1558608802?uo=2"
    },
    {
      "rank": 99,
      "apple_id": "1667542175",
      "name": "Auf eine weiß-blaue Tasse",
      "artist": "Bayern.de",
      "artwork": "https://is1-ssl.mzstatic.com/image/thumb/Podcasts113/v4/9d/cd/01/9dcd01b7-5a06-24ab-5584-4ee141ccec40/mza_5153853817547764023.jpg/170x170bb.png",
      "genre": "Government",
      "genre_id": "1511",
      "url": "https://podcasts.apple.com/de/podcast/auf-eine-wei%C3%9F-blaue-tasse/id1667542175?uo=2"
    },
    {
      "rank": 100,
      "apple_id": "1656161127",
      "name": "The Merge",
      "artist": "The Merge",
      "artwork": "https://is1-ssl.mzstatic.com/image/thumb/Podcasts126/v4/f5/c6/a9/f5c6a9c8-d491-8d0c-d333-05b9a5af8998/mza_7895861344057423941.jpg/170x170bb.png",
      "genre": "Government",
      "genre_id": "1511",
      "url": "https://podcasts.apple.com/de/podcast/the-merge/id1656161127?uo=2"
    },
    {
      "rank": 101,
      "apple_id": "1562349360",
      "name": "Let´s Staat - Inspirationen aus dem Staatsapparat",
      "artist": "Dr. Dorit Bosch",
      "artwork": "https://is1-ssl.mzstatic.com/image/thumb/Podcasts115/v4/32/2c/5a/322c5ac5-9779-f278-68b4-a4620d847a35/mza_17588884299038152585.png/170x170bb.png",
      "genre": "Government",
      "genre_id": "1511",
      "url": "https://podcasts.apple.com/de/podcast/let-s-staat-inspirationen-aus-dem-staatsapparat/id1562349360?uo=2"
    },
    {
      "rank": 102,
      "apple_id": "1519689024",
      "name": "Democracy Paradox",
      "artist": "Justin Kempf",
      "artwork": "https://is1-ssl.mzstatic.com/image/thumb/Podcasts211/v4/63/40/f6/6340f688-ad0a-7683-8c70-d681e9cfb3b8/mza_9425017025029485712.jpg/170x170bb.png",
      "genre": "Government",
      "genre_id": "1511",
      "url": "https://podcasts.apple.com/de/podcast/democracy-paradox/id1519689024?uo=2"
    },
    {
      "rank": 103,
      "apple_id": "345287512",
      "name": "detektor.fm | Politik",
      "artist": "detektor.fm – Das Podcast-Radio",
      "artwork": "https://is1-ssl.mzstatic.com/image/thumb/Podcasts125/v4/dc/a9/e5/dca9e53a-60de-fc60-7f2f-1868632e53a5/mza_7386154627050152284.jpeg/170x170bb.png",
      "genre": "Government",
      "genre_id": "1511",
      "url": "https://podcasts.apple.com/de/podcast/detektor-fm-politik/id345287512?uo=2"
    },
    {
      "rank": 104,
      "apple_id": "1885584812",
      "name": "Nass und nachhaltig – Klima, Landwirtschaft und die Zukunft unserer Moorböden",
      "artist": "Zukunft – Umwelt – Gesellschaft (ZUG) gGmbH",
      "artwork": "https://is1-ssl.mzstatic.com/image/thumb/Podcasts211/v4/f1/27/d6/f127d6f6-3198-b03d-8235-ca787b561284/mza_15046557196375284206.jpg/170x170bb.png",
      "genre": "Government",
      "genre_id": "1511",
      "url": "https://podcasts.apple.com/de/podcast/nass-und-nachhaltig-klima-landwirtschaft-und-die-zukunft/id1885584812?uo=2"
    },
    {
      "rank": 105,
      "apple_id": "1535478326",
      "name": "Datenfreiheit!",
      "artist": "Der Landesbeauftragte für den Datenschutz und die Informationsfreiheit Baden-Württemberg",
      "artwork": "https://is1-ssl.mzstatic.com/image/thumb/Podcasts124/v4/60/be/5f/60be5f7e-fa26-abb8-64fb-7c0b1aeff2cc/mza_16495755575348407044.png/170x170bb.png",
      "genre": "Government",
      "genre_id": "1511",
      "url": "https://podcasts.apple.com/de/podcast/datenfreiheit/id1535478326?uo=2"
    },
    {
      "rank": 106,
      "apple_id": "1242537529",
      "name": "What Trump Can Teach Us About Con Law",
      "artist": "Roman Mars",
      "artwork": "https://is1-ssl.mzstatic.com/image/thumb/Podcasts211/v4/3f/d5/24/3fd524dc-7825-1639-4b30-b5e97cb5d509/mza_8599492171491331308.jpg/170x170bb.png",
      "genre": "Government",
      "genre_id": "1511",
      "url": "https://podcasts.apple.com/de/podcast/what-trump-can-teach-us-about-con-law/id1242537529?uo=2"
    },
    {
      "rank": 107,
      "apple_id": "1896907127",
      "name": "AUF DEM RADAR",
      "artist": "Verfassungsschutz Nordrhein-Westfalen",
      "artwork": "https://is1-ssl.mzstatic.com/image/thumb/Podcasts211/v4/0d/7f/6f/0d7f6f88-bb1e-a149-f60b-f5d74161c1c8/mza_274592374760661312.jpg/170x170bb.png",
      "genre": "Government",
      "genre_id": "1511",
      "url": "https://podcasts.apple.com/de/podcast/auf-dem-radar/id1896907127?uo=2"
    },
    {
      "rank": 108,
      "apple_id": "1677424942",
      "name": "DC EKG",
      "artist": "Stay On Course Studios",
      "artwork": "https://is1-ssl.mzstatic.com/image/thumb/Podcasts211/v4/52/5b/fc/525bfcbb-ee78-6288-6956-fe7271920570/mza_11223338205950294637.jpg/170x170bb.png",
      "genre": "Government",
      "genre_id": "1511",
      "url": "https://podcasts.apple.com/de/podcast/dc-ekg/id1677424942?uo=2"
    },
    {
      "rank": 109,
      "apple_id": "1847986591",
      "name": "Disclosure",
      "artist": "Bloomberg",
      "artwork": "https://is1-ssl.mzstatic.com/image/thumb/Podcasts211/v4/d2/51/11/d251111f-a04e-c5d7-6891-8ca025a29496/mza_7887905272101077993.jpg/170x170bb.png",
      "genre": "Government",
      "genre_id": "1511",
      "url": "https://podcasts.apple.com/de/podcast/disclosure/id1847986591?uo=2"
    },
    {
      "rank": 110,
      "apple_id": "1896632132",
      "name": "EUrawLaw",
      "artist": "Jean Monnet Chair",
      "artwork": "https://is1-ssl.mzstatic.com/image/thumb/Podcasts221/v4/08/31/d9/0831d9b9-9b3f-9ba4-6937-0d2d66681ee0/mza_11018667563749786275.jpg/170x170bb.png",
      "genre": "Government",
      "genre_id": "1511",
      "url": "https://podcasts.apple.com/de/podcast/eurawlaw/id1896632132?uo=2"
    },
    {
      "rank": 111,
      "apple_id": "1484110214",
      "name": "Inside Briefing with the Institute for Government",
      "artist": "Institute for Government",
      "artwork": "https://is1-ssl.mzstatic.com/image/thumb/Podcasts211/v4/40/f1/0a/40f10a85-600a-2121-809f-169a6c7eb0b4/mza_18065194289637157593.jpeg/170x170bb.png",
      "genre": "Government",
      "genre_id": "1511",
      "url": "https://podcasts.apple.com/de/podcast/inside-briefing-with-the-institute-for-government/id1484110214?uo=2"
    },
    {
      "rank": 112,
      "apple_id": "1517386671",
      "name": "LandTalk Bayern - Der Polit-Podcast, der hinterfragt.",
      "artist": "Caro Matzko, Florian Schairer",
      "artwork": "https://is1-ssl.mzstatic.com/image/thumb/Podcasts116/v4/f3/f3/1e/f3f31ed5-130b-676c-15a9-b0d12f791e33/mza_1984845009393727404.jpg/170x170bb.png",
      "genre": "Government",
      "genre_id": "1511",
      "url": "https://podcasts.apple.com/de/podcast/landtalk-bayern-der-polit-podcast-der-hinterfragt/id1517386671?uo=2"
    },
    {
      "rank": 113,
      "apple_id": "1441966413",
      "name": "EU Scream",
      "artist": "EU Scream",
      "artwork": "https://is1-ssl.mzstatic.com/image/thumb/Podcasts221/v4/0a/32/37/0a3237fa-ee30-f5bf-6f45-e3edb9f3db4c/mza_8396685473795308215.jpg/170x170bb.png",
      "genre": "Government",
      "genre_id": "1511",
      "url": "https://podcasts.apple.com/de/podcast/eu-scream/id1441966413?uo=2"
    },
    {
      "rank": 114,
      "apple_id": "1860524961",
      "name": "Grenzgeschichten I Grenzgänger Podcast - Leben & Arbeiten zwischen Deutschland und Luxemburg",
      "artist": "Ministère de la Famille, des Solidarités,  du Vivre ensemble et de l’Accueil Podcasts",
      "artwork": "https://is1-ssl.mzstatic.com/image/thumb/Podcasts221/v4/36/86/54/368654c3-e06d-00ba-c196-99462fda130d/mza_17410296283830067053.jpeg/170x170bb.png",
      "genre": "Government",
      "genre_id": "1511",
      "url": "https://podcasts.apple.com/de/podcast/grenzgeschichten-i-grenzg%C3%A4nger-podcast-leben-arbeiten/id1860524961?uo=2"
    },
    {
      "rank": 115,
      "apple_id": "1843102764",
      "name": "QUARTIER LIBRE",
      "artist": "Armée de Terre recrute",
      "artwork": "https://is1-ssl.mzstatic.com/image/thumb/Podcasts221/v4/e0/a9/38/e0a9383f-e3b5-c731-14de-b9323dd32638/mza_12502346871244071605.jpg/170x170bb.png",
      "genre": "Government",
      "genre_id": "1511",
      "url": "https://podcasts.apple.com/de/podcast/quartier-libre/id1843102764?uo=2"
    },
    {
      "rank": 116,
      "apple_id": "1848469673",
      "name": "Brief Recess: A Legal Podcast with Michael Foote & Mélissa Malebranche",
      "artist": "Exactly Right and iHeartPodcasts",
      "artwork": "https://is1-ssl.mzstatic.com/image/thumb/Podcasts221/v4/59/ca/fe/59cafe58-4b99-90a1-002f-dcc2e392c219/mza_5313858641470066782.jpg/170x170bb.png",
      "genre": "Government",
      "genre_id": "1511",
      "url": "https://podcasts.apple.com/de/podcast/brief-recess-a-legal-podcast-with-michael-foote/id1848469673?uo=2"
    },
    {
      "rank": 117,
      "apple_id": "1801477861",
      "name": "Jacques Baud - Ukraine US",
      "artist": "Jacques Baud",
      "artwork": "https://is1-ssl.mzstatic.com/image/thumb/Podcasts221/v4/07/70/a2/0770a200-da79-b66b-4a0c-c196e6a1788d/mza_6441602041152140822.jpg/170x170bb.png",
      "genre": "Government",
      "genre_id": "1511",
      "url": "https://podcasts.apple.com/de/podcast/jacques-baud-ukraine-us/id1801477861?uo=2"
    },
    {
      "rank": 118,
      "apple_id": "1635295907",
      "name": "下班瀚你聊",
      "artist": "風傳媒",
      "artwork": "https://is1-ssl.mzstatic.com/image/thumb/Podcasts221/v4/e3/6c/5a/e36c5ae6-2f13-a5c6-f356-f90c09b34881/mza_14619467213886028074.jpeg/170x170bb.png",
      "genre": "Government",
      "genre_id": "1511",
      "url": "https://podcasts.apple.com/de/podcast/%E4%B8%8B%E7%8F%AD%E7%80%9A%E4%BD%A0%E8%81%8A/id1635295907?uo=2"
    },
    {
      "rank": 119,
      "apple_id": "1533560948",
      "name": "The Fact Hunter",
      "artist": "Delmarva Studios",
      "artwork": "https://is1-ssl.mzstatic.com/image/thumb/Podcasts211/v4/1d/b9/16/1db916b0-b4bd-dafe-7679-eab5fa2a7568/mza_6577621883931652863.jpg/170x170bb.png",
      "genre": "Government",
      "genre_id": "1511",
      "url": "https://podcasts.apple.com/de/podcast/the-fact-hunter/id1533560948?uo=2"
    },
    {
      "rank": 120,
      "apple_id": "1614411002",
      "name": "Sozial? Geht immer!",
      "artist": "Sozialverband Deutschland, SoVD-Landesverband Hamburg e.V.",
      "artwork": "https://is1-ssl.mzstatic.com/image/thumb/Podcasts116/v4/33/5a/bd/335abd63-6985-9eb4-6773-d2ecc386676e/mza_14816034688281615305.png/170x170bb.png",
      "genre": "Government",
      "genre_id": "1511",
      "url": "https://podcasts.apple.com/de/podcast/sozial-geht-immer/id1614411002?uo=2"
    },
    {
      "rank": 121,
      "apple_id": "1537151427",
      "name": "Recht so?!",
      "artist": "Bundesministerium der Justiz und für Verbraucherschutz",
      "artwork": "https://is1-ssl.mzstatic.com/image/thumb/Podcasts114/v4/b2/22/d7/b222d7a7-72ce-bb3f-8206-ba7d00ac8091/mza_13067501810393297403.jpg/170x170bb.png",
      "genre": "Government",
      "genre_id": "1511",
      "url": "https://podcasts.apple.com/de/podcast/recht-so/id1537151427?uo=2"
    },
    {
      "rank": 122,
      "apple_id": "1526423715",
      "name": "Digital Government Podcast",
      "artist": "e-Governance Academy",
      "artwork": "https://is1-ssl.mzstatic.com/image/thumb/Podcasts211/v4/f3/57/34/f3573426-b169-5caf-d165-96509b08ad1a/mza_11331120526339859059.jpg/170x170bb.png",
      "genre": "Government",
      "genre_id": "1511",
      "url": "https://podcasts.apple.com/de/podcast/digital-government-podcast/id1526423715?uo=2"
    },
    {
      "rank": 123,
      "apple_id": "1695973105",
      "name": "Audio Briefs",
      "artist": "Center for Strategic and International Studies",
      "artwork": "https://is1-ssl.mzstatic.com/image/thumb/Podcasts116/v4/6e/06/20/6e0620a5-6e3c-b104-51dc-78d0202f60a7/mza_15455099455822349087.jpg/170x170bb.png",
      "genre": "Government",
      "genre_id": "1511",
      "url": "https://podcasts.apple.com/de/podcast/audio-briefs/id1695973105?uo=2"
    },
    {
      "rank": 124,
      "apple_id": "1671518571",
      "name": "Lobbyversum",
      "artist": "elfnullelf GmbH",
      "artwork": "https://is1-ssl.mzstatic.com/image/thumb/Podcasts126/v4/9f/bf/49/9fbf49b4-d7b0-0ac0-708c-6ae84013220f/mza_13696176794251549206.png/170x170bb.png",
      "genre": "Government",
      "genre_id": "1511",
      "url": "https://podcasts.apple.com/de/podcast/lobbyversum/id1671518571?uo=2"
    },
    {
      "rank": 125,
      "apple_id": "1795734509",
      "name": "The Oath and The Office",
      "artist": "Two Squared Media Productions",
      "artwork": "https://is1-ssl.mzstatic.com/image/thumb/Podcasts221/v4/f3/04/4d/f3044daa-613e-02b8-6db4-6eaccc91c7f2/mza_13507250191369452450.jpg/170x170bb.png",
      "genre": "Government",
      "genre_id": "1511",
      "url": "https://podcasts.apple.com/de/podcast/the-oath-and-the-office/id1795734509?uo=2"
    },
    {
      "rank": 126,
      "apple_id": "1589058069",
      "name": "Fritz Bauer Hörbuch",
      "artist": "Bundesministerium der Justiz und für Verbraucherschutz",
      "artwork": "https://is1-ssl.mzstatic.com/image/thumb/Podcasts115/v4/5a/e9/5e/5ae95e85-5db8-3d41-0930-1724f8108743/mza_6632431769473232936.jpg/170x170bb.png",
      "genre": "Government",
      "genre_id": "1511",
      "url": "https://podcasts.apple.com/de/podcast/fritz-bauer-h%C3%B6rbuch/id1589058069?uo=2"
    },
    {
      "rank": 127,
      "apple_id": "1645885248",
      "name": "The Langley Files: CIA's Podcast",
      "artist": "Central Intelligence Agency",
      "artwork": "https://is1-ssl.mzstatic.com/image/thumb/Podcasts221/v4/53/6e/5d/536e5d12-39c5-9577-cf82-067cc1ec52a3/mza_1173598155674654115.jpg/170x170bb.png",
      "genre": "Government",
      "genre_id": "1511",
      "url": "https://podcasts.apple.com/de/podcast/the-langley-files-cias-podcast/id1645885248?uo=2"
    },
    {
      "rank": 128,
      "apple_id": "1499271317",
      "name": "Political Theory 101",
      "artist": "Political Theory 101",
      "artwork": "https://is1-ssl.mzstatic.com/image/thumb/Podcasts125/v4/e0/c8/cb/e0c8cbb5-3bc5-0238-4ca0-8d07240998bf/mza_16359021133979975311.jpg/170x170bb.png",
      "genre": "Government",
      "genre_id": "1511",
      "url": "https://podcasts.apple.com/de/podcast/political-theory-101/id1499271317?uo=2"
    },
    {
      "rank": 129,
      "apple_id": "1801347486",
      "name": "طاهر المعتز بالله - ماذا يحدث؟",
      "artist": "Taher El Moataz Bellah",
      "artwork": "https://is1-ssl.mzstatic.com/image/thumb/Podcasts211/v4/05/c3/da/05c3da41-69c5-9a72-37d6-ff954da7de75/mza_1196304787538640900.jpg/170x170bb.png",
      "genre": "Government",
      "genre_id": "1511",
      "url": "https://podcasts.apple.com/de/podcast/%D8%B7%D8%A7%D9%87%D8%B1-%D8%A7%D9%84%D9%85%D8%B9%D8%AA%D8%B2-%D8%A8%D8%A7%D9%84%D9%84%D9%87-%D9%85%D8%A7%D8%B0%D8%A7-%D9%8A%D8%AD%D8%AF%D8%AB/id1801347486?uo=2"
    },
    {
      "rank": 130,
      "apple_id": "1455877680",
      "name": "A Voz do Brasil",
      "artist": "Rádio Senado",
      "artwork": "https://is1-ssl.mzstatic.com/image/thumb/Podcasts126/v4/5c/5e/52/5c5e5202-64a8-0d31-e64b-841553c9b0f5/mza_2517324362994125740.jpeg/170x170bb.png",
      "genre": "Government",
      "genre_id": "1511",
      "url": "https://podcasts.apple.com/de/podcast/a-voz-do-brasil/id1455877680?uo=2"
    },
    {
      "rank": 131,
      "apple_id": "1888150417",
      "name": "Landratsamt Vogtlandkreis",
      "artist": "Landratsamt Vogtlandkreis",
      "artwork": "https://is1-ssl.mzstatic.com/image/thumb/Podcasts221/v4/b6/9d/cb/b69dcb8d-454f-1d96-4941-383dbb8cb9e4/mza_248665160940537129.jpg/170x170bb.png",
      "genre": "Government",
      "genre_id": "1511",
      "url": "https://podcasts.apple.com/de/podcast/landratsamt-vogtlandkreis/id1888150417?uo=2"
    },
    {
      "rank": 132,
      "apple_id": "1380336613",
      "name": "The Trade Guys",
      "artist": "CSIS  |  Center for Strategic and International Studies",
      "artwork": "https://is1-ssl.mzstatic.com/image/thumb/Podcasts211/v4/24/09/f1/2409f1b7-2224-8ba2-587f-978f370c10f2/mza_14365964162392684033.jpg/170x170bb.png",
      "genre": "Government",
      "genre_id": "1511",
      "url": "https://podcasts.apple.com/de/podcast/the-trade-guys/id1380336613?uo=2"
    },
    {
      "rank": 133,
      "apple_id": "1459232606",
      "name": "سقراط مع عمر الجريسي",
      "artist": "ثمانية/ thmanyah",
      "artwork": "https://is1-ssl.mzstatic.com/image/thumb/Podcasts221/v4/af/83/c1/af83c182-c1fe-2b22-ae7a-19a7119ceef5/mza_11011506470849485523.jpg/170x170bb.png",
      "genre": "Government",
      "genre_id": "1511",
      "url": "https://podcasts.apple.com/de/podcast/%D8%B3%D9%82%D8%B1%D8%A7%D8%B7-%D9%85%D8%B9-%D8%B9%D9%85%D8%B1-%D8%A7%D9%84%D8%AC%D8%B1%D9%8A%D8%B3%D9%8A/id1459232606?uo=2"
    },
    {
      "rank": 134,
      "apple_id": "1790305658",
      "name": "The CDR Policy Scoop",
      "artist": "Eve Tamme and Sebastian Manhart",
      "artwork": "https://is1-ssl.mzstatic.com/image/thumb/Podcasts211/v4/0d/95/ab/0d95ab71-c59f-77fe-c447-4be73d9405c1/mza_17319006234597257378.jpeg/170x170bb.png",
      "genre": "Government",
      "genre_id": "1511",
      "url": "https://podcasts.apple.com/de/podcast/the-cdr-policy-scoop/id1790305658?uo=2"
    },
    {
      "rank": 135,
      "apple_id": "926521563",
      "name": "Hudson Institute Events Podcast",
      "artist": "Hudson Institute",
      "artwork": "https://is1-ssl.mzstatic.com/image/thumb/Podcasts211/v4/16/35/7c/16357cf9-dfc8-74b4-e1b6-7d55cf2697d6/mza_15162408727572412414.jpg/170x170bb.png",
      "genre": "Government",
      "genre_id": "1511",
      "url": "https://podcasts.apple.com/de/podcast/hudson-institute-events-podcast/id926521563?uo=2"
    },
    {
      "rank": 136,
      "apple_id": "1179984273",
      "name": "Defence & Security Podcast Network",
      "artist": "Momentum Media",
      "artwork": "https://is1-ssl.mzstatic.com/image/thumb/Podcasts221/v4/0f/f4/7e/0ff47e56-fc11-0182-1011-53290c8e0248/mza_17759977726912050717.jpg/170x170bb.png",
      "genre": "Government",
      "genre_id": "1511",
      "url": "https://podcasts.apple.com/de/podcast/defence-security-podcast-network/id1179984273?uo=2"
    },
    {
      "rank": 137,
      "apple_id": "1884704967",
      "name": "Kaffee mit Niels",
      "artist": "Niels Geuking MdEP",
      "artwork": "https://is1-ssl.mzstatic.com/image/thumb/Podcasts211/v4/e6/d6/fc/e6d6fc35-7ada-0e9b-f398-a5852ad6700d/mza_14180565404411469621.jpg/170x170bb.png",
      "genre": "Government",
      "genre_id": "1511",
      "url": "https://podcasts.apple.com/de/podcast/kaffee-mit-niels/id1884704967?uo=2"
    },
    {
      "rank": 138,
      "apple_id": "1782868939",
      "name": "Streitcafé",
      "artist": "© Jugend debattiert | PODCAST EINS",
      "artwork": "https://is1-ssl.mzstatic.com/image/thumb/Podcasts221/v4/be/a9/47/bea94701-d0e9-2c2f-db62-f8c8098b6d14/mza_9683934195522572448.jpeg/170x170bb.png",
      "genre": "Government",
      "genre_id": "1511",
      "url": "https://podcasts.apple.com/de/podcast/streitcaf%C3%A9/id1782868939?uo=2"
    },
    {
      "rank": 139,
      "apple_id": "1727769913",
      "name": "Law and Chaos",
      "artist": "Liz Dye; Andrew Torrez",
      "artwork": "https://is1-ssl.mzstatic.com/image/thumb/Podcasts211/v4/e0/c5/3c/e0c53c48-ebc7-a3de-b78e-0c413b079d45/mza_6011918820670793028.jpeg/170x170bb.png",
      "genre": "Government",
      "genre_id": "1511",
      "url": "https://podcasts.apple.com/de/podcast/law-and-chaos/id1727769913?uo=2"
    },
    {
      "rank": 140,
      "apple_id": "1866698931",
      "name": "Taiwan Frontlines: Taiwan in the Global Arena",
      "artist": "The German Marshall Fund",
      "artwork": "https://is1-ssl.mzstatic.com/image/thumb/Podcasts221/v4/b5/58/36/b5583653-92ba-122c-5c09-f3c1f5270be1/mza_4960147503706538109.jpg/170x170bb.png",
      "genre": "Government",
      "genre_id": "1511",
      "url": "https://podcasts.apple.com/de/podcast/taiwan-frontlines-taiwan-in-the-global-arena/id1866698931?uo=2"
    },
    {
      "rank": 141,
      "apple_id": "1534829787",
      "name": "A Matter of Degrees",
      "artist": "Dr. Leah Stokes, Dr. Katharine Wilkinson",
      "artwork": "https://is1-ssl.mzstatic.com/image/thumb/Podcasts211/v4/27/04/6a/27046a54-ce79-6abe-25ca-f947e4cd4ded/mza_186537311319721225.png/170x170bb.png",
      "genre": "Government",
      "genre_id": "1511",
      "url": "https://podcasts.apple.com/de/podcast/a-matter-of-degrees/id1534829787?uo=2"
    },
    {
      "rank": 142,
      "apple_id": "1420216970",
      "name": "DSR's Words Matter",
      "artist": "The DSR Network",
      "artwork": "https://is1-ssl.mzstatic.com/image/thumb/Podcasts221/v4/ee/2f/c9/ee2fc9b5-ecbf-e448-afb0-cf873eac4b57/mza_1332143550605474815.jpeg/170x170bb.png",
      "genre": "Government",
      "genre_id": "1511",
      "url": "https://podcasts.apple.com/de/podcast/dsrs-words-matter/id1420216970?uo=2"
    },
    {
      "rank": 143,
      "apple_id": "1533447022",
      "name": "The Deduction",
      "artist": "Tax Foundation",
      "artwork": "https://is1-ssl.mzstatic.com/image/thumb/Podcasts211/v4/51/57/65/51576513-d15f-0ef4-0610-a96f31030d7f/mza_5330539550964573123.jpg/170x170bb.png",
      "genre": "Government",
      "genre_id": "1511",
      "url": "https://podcasts.apple.com/de/podcast/the-deduction/id1533447022?uo=2"
    },
    {
      "rank": 144,
      "apple_id": "1677512457",
      "name": "zukunft Land",
      "artist": "© LandFrauenverband | PODCAST EINS",
      "artwork": "https://is1-ssl.mzstatic.com/image/thumb/Podcasts116/v4/75/cc/0a/75cc0a42-ca21-bf65-94a0-074c7be09f1a/mza_11805971250460614399.jpeg/170x170bb.png",
      "genre": "Government",
      "genre_id": "1511",
      "url": "https://podcasts.apple.com/de/podcast/zukunft-land/id1677512457?uo=2"
    },
    {
      "rank": 145,
      "apple_id": "1740955743",
      "name": "Politika in kokice",
      "artist": "Robert Celestina, Aleš Trtnik in Aljaž Plevnik",
      "artwork": "https://is1-ssl.mzstatic.com/image/thumb/Podcasts211/v4/06/1e/1e/061e1e77-331e-6dac-0d56-3c5ee80799d0/mza_17973071569200682993.jpg/170x170bb.png",
      "genre": "Government",
      "genre_id": "1511",
      "url": "https://podcasts.apple.com/de/podcast/politika-in-kokice/id1740955743?uo=2"
    },
    {
      "rank": 146,
      "apple_id": "1594573645",
      "name": "Romanzo Quirinale",
      "artist": "Marco Damilano – Chora Media",
      "artwork": "https://is1-ssl.mzstatic.com/image/thumb/Podcasts221/v4/cd/47/b3/cd47b33a-fbc0-4272-c748-9ad3d2e4e023/mza_4257688947708511761.jpg/170x170bb.png",
      "genre": "Government",
      "genre_id": "1511",
      "url": "https://podcasts.apple.com/de/podcast/romanzo-quirinale/id1594573645?uo=2"
    },
    {
      "rank": 147,
      "apple_id": "1463163931",
      "name": "OECD Podcasts",
      "artist": "OECD",
      "artwork": "https://is1-ssl.mzstatic.com/image/thumb/Podcasts112/v4/56/20/8f/56208f12-3d75-d257-f232-fceb11fe8f0c/mza_4583999292594794146.jpeg/170x170bb.png",
      "genre": "Government",
      "genre_id": "1511",
      "url": "https://podcasts.apple.com/de/podcast/oecd-podcasts/id1463163931?uo=2"
    },
    {
      "rank": 148,
      "apple_id": "1652693488",
      "name": "Inside EMS",
      "artist": "EMS1 Podcasts",
      "artwork": "https://is1-ssl.mzstatic.com/image/thumb/Podcasts126/v4/80/aa/91/80aa916e-3d01-4e8b-dd1c-b1b38ef9ed5f/mza_10710940712412637255.png/170x170bb.png",
      "genre": "Government",
      "genre_id": "1511",
      "url": "https://podcasts.apple.com/de/podcast/inside-ems/id1652693488?uo=2"
    },
    {
      "rank": 149,
      "apple_id": "1896490924",
      "name": "We're All Going To Die!",
      "artist": "Justin Young",
      "artwork": "https://is1-ssl.mzstatic.com/image/thumb/Podcasts211/v4/48/81/bf/4881bffb-a0be-5a17-73be-df231ebd3db4/mza_15549881063401953474.jpeg/170x170bb.png",
      "genre": "Government",
      "genre_id": "1511",
      "url": "https://podcasts.apple.com/de/podcast/were-all-going-to-die/id1896490924?uo=2"
    },
    {
      "rank": 150,
      "apple_id": "1606431101",
      "name": "Breaking Hezbollah's Golden Rule",
      "artist": "Washington Institute",
      "artwork": "https://is1-ssl.mzstatic.com/image/thumb/Podcasts116/v4/15/5c/40/155c40b1-ae47-6957-b392-7901c7d56e56/mza_12988040116437521260.jpeg/170x170bb.png",
      "genre": "Government",
      "genre_id": "1511",
      "url": "https://podcasts.apple.com/de/podcast/breaking-hezbollahs-golden-rule/id1606431101?uo=2"
    },
    {
      "rank": 151,
      "apple_id": "1554485181",
      "name": "Total lokal ",
      "artist": "Hessische Landeszentrale für politische Bildung",
      "artwork": "https://is1-ssl.mzstatic.com/image/thumb/Podcasts114/v4/f4/d2/78/f4d27847-647c-2ded-2aed-a16b1c4ff9f2/mza_9098494923777502782.jpg/170x170bb.png",
      "genre": "Government",
      "genre_id": "1511",
      "url": "https://podcasts.apple.com/de/podcast/total-lokal/id1554485181?uo=2"
    },
    {
      "rank": 152,
      "apple_id": "1451586988",
      "name": "Fundraising Podcast",
      "artist": "Jan Uekermann",
      "artwork": "https://is1-ssl.mzstatic.com/image/thumb/Podcasts125/v4/85/51/ee/8551eee2-54aa-eb2b-b55e-bcf3e73ea8cc/mza_9170562061351602323.png/170x170bb.png",
      "genre": "Government",
      "genre_id": "1511",
      "url": "https://podcasts.apple.com/de/podcast/fundraising-podcast/id1451586988?uo=2"
    },
    {
      "rank": 153,
      "apple_id": "284675702",
      "name": "Red Eye Radio",
      "artist": "Cumulus Podcast Network",
      "artwork": "https://is1-ssl.mzstatic.com/image/thumb/Podcasts221/v4/64/b9/36/64b93689-a27c-fc6b-ebd0-d8052bd4683a/mza_3110521675706361306.jpg/170x170bb.png",
      "genre": "Government",
      "genre_id": "1511",
      "url": "https://podcasts.apple.com/de/podcast/red-eye-radio/id284675702?uo=2"
    },
    {
      "rank": 154,
      "apple_id": "1503676459",
      "name": "Social Discipline",
      "artist": "Social Discipline",
      "artwork": "https://is1-ssl.mzstatic.com/image/thumb/Podcasts125/v4/ec/ee/31/ecee3119-9675-b573-0cca-7a55f7dfb0f6/mza_17449663808858944625.jpg/170x170bb.png",
      "genre": "Government",
      "genre_id": "1511",
      "url": "https://podcasts.apple.com/de/podcast/social-discipline/id1503676459?uo=2"
    },
    {
      "rank": 155,
      "apple_id": "1599371423",
      "name": "Data-Smart City Pod",
      "artist": "Data-Smart City Solutions",
      "artwork": "https://is1-ssl.mzstatic.com/image/thumb/Podcasts116/v4/89/cd/0c/89cd0cda-28fa-32e3-bc6f-0897842f9292/mza_2869110469706083612.jpg/170x170bb.png",
      "genre": "Government",
      "genre_id": "1511",
      "url": "https://podcasts.apple.com/de/podcast/data-smart-city-pod/id1599371423?uo=2"
    },
    {
      "rank": 156,
      "apple_id": "1719447867",
      "name": "Pensez stratégique",
      "artist": "Ministère des Armées",
      "artwork": "https://is1-ssl.mzstatic.com/image/thumb/Podcasts116/v4/43/80/c3/4380c346-4c73-3246-b3c5-b52d8682f071/mza_2209484690655259229.jpg/170x170bb.png",
      "genre": "Government",
      "genre_id": "1511",
      "url": "https://podcasts.apple.com/de/podcast/pensez-strat%C3%A9gique/id1719447867?uo=2"
    },
    {
      "rank": 157,
      "apple_id": "1612220659",
      "name": "Perspektive: Politik",
      "artist": "Eric Eigendorf und Konstantin Pott",
      "artwork": "https://is1-ssl.mzstatic.com/image/thumb/Podcasts116/v4/5f/40/74/5f40746e-d52f-f979-696c-8ed2a5feedda/mza_17652690069871292081.jpg/170x170bb.png",
      "genre": "Government",
      "genre_id": "1511",
      "url": "https://podcasts.apple.com/de/podcast/perspektive-politik/id1612220659?uo=2"
    },
    {
      "rank": 158,
      "apple_id": "878381973",
      "name": "SBK-RLP Podcast",
      "artist": "Steuerberaterkammer Rheinland-Pfalz",
      "artwork": "https://is1-ssl.mzstatic.com/image/thumb/Podcasts125/v4/1b/97/80/1b978006-ed57-73a0-5b1d-8b44fb120cae/mza_9865335189785928155.png/170x170bb.png",
      "genre": "Government",
      "genre_id": "1511",
      "url": "https://podcasts.apple.com/de/podcast/sbk-rlp-podcast/id878381973?uo=2"
    },
    {
      "rank": 159,
      "apple_id": "1617685492",
      "name": "Southeast Asia Radio",
      "artist": "CSIS | Center for Strategic and International Studies",
      "artwork": "https://is1-ssl.mzstatic.com/image/thumb/Podcasts211/v4/38/46/8a/38468a0e-3c74-44e6-2d7d-2ab4596a0d09/mza_4947141585883682887.jpeg/170x170bb.png",
      "genre": "Government",
      "genre_id": "1511",
      "url": "https://podcasts.apple.com/de/podcast/southeast-asia-radio/id1617685492?uo=2"
    },
    {
      "rank": 160,
      "apple_id": "1670089106",
      "name": "Stalnuhhin | Стальнухин",
      "artist": "Mihhail Stalnuhhin",
      "artwork": "https://is1-ssl.mzstatic.com/image/thumb/Podcasts116/v4/30/e5/37/30e537de-8b0b-8fa6-01e0-43381e19191d/mza_17507859384824798956.jpg/170x170bb.png",
      "genre": "Government",
      "genre_id": "1511",
      "url": "https://podcasts.apple.com/de/podcast/stalnuhhin-%D1%81%D1%82%D0%B0%D0%BB%D1%8C%D0%BD%D1%83%D1%85%D0%B8%D0%BD/id1670089106?uo=2"
    },
    {
      "rank": 161,
      "apple_id": "1645315514",
      "name": "Простая экономика",
      "artist": "Простая экономика",
      "artwork": "https://is1-ssl.mzstatic.com/image/thumb/Podcasts112/v4/9f/b1/2e/9fb12ed4-6958-2064-71a8-e11f247d586c/mza_13129293402215154.png/170x170bb.png",
      "genre": "Government",
      "genre_id": "1511",
      "url": "https://podcasts.apple.com/de/podcast/%D0%BF%D1%80%D0%BE%D1%81%D1%82%D0%B0%D1%8F-%D1%8D%D0%BA%D0%BE%D0%BD%D0%BE%D0%BC%D0%B8%D0%BA%D0%B0/id1645315514?uo=2"
    },
    {
      "rank": 162,
      "apple_id": "1475380926",
      "name": "Targeted Individual: Since 1994 Implanted tracked and tortured",
      "artist": "G. A.",
      "artwork": "https://is1-ssl.mzstatic.com/image/thumb/Podcasts115/v4/20/fb/c0/20fbc0e4-4bf3-6a88-cc73-03c2100a5a51/mza_606421514313215266.jpg/170x170bb.png",
      "genre": "Government",
      "genre_id": "1511",
      "url": "https://podcasts.apple.com/de/podcast/targeted-individual-since-1994-implanted-tracked-and/id1475380926?uo=2"
    },
    {
      "rank": 163,
      "apple_id": "1681372480",
      "name": "Edi Rama Podcast",
      "artist": "Edi Rama",
      "artwork": "https://is1-ssl.mzstatic.com/image/thumb/Podcasts116/v4/65/94/02/6594028a-f2a1-cd66-c776-8686f0ab9046/mza_4266173102819444188.jpg/170x170bb.png",
      "genre": "Government",
      "genre_id": "1511",
      "url": "https://podcasts.apple.com/de/podcast/edi-rama-podcast/id1681372480?uo=2"
    },
    {
      "rank": 164,
      "apple_id": "1279728527",
      "name": "KOMMUNALPerspektive | Die ungewöhnlichste Fraktionsgemeinschaft Deutschlands",
      "artist": "Christian Erhardt",
      "artwork": "https://is1-ssl.mzstatic.com/image/thumb/Podcasts211/v4/3b/71/55/3b715539-9538-f9e5-c27d-85647c877cbb/mza_8559994520910992352.png/170x170bb.png",
      "genre": "Government",
      "genre_id": "1511",
      "url": "https://podcasts.apple.com/de/podcast/kommunalperspektive-die-ungew%C3%B6hnlichste-fraktionsgemeinschaft/id1279728527?uo=2"
    },
    {
      "rank": 165,
      "apple_id": "1686733153",
      "name": "Nächste Links",
      "artist": "Nächste Links",
      "artwork": "https://is1-ssl.mzstatic.com/image/thumb/Podcasts126/v4/e2/30/6d/e2306d19-8860-cda1-1f18-ce41340e7ce2/mza_13185286060570286366.jpg/170x170bb.png",
      "genre": "Government",
      "genre_id": "1511",
      "url": "https://podcasts.apple.com/de/podcast/n%C3%A4chste-links/id1686733153?uo=2"
    },
    {
      "rank": 166,
      "apple_id": "1896884336",
      "name": "Something Different with John and Sarah",
      "artist": "Something Different",
      "artwork": "https://is1-ssl.mzstatic.com/image/thumb/PodcastSource221/v4/30/d7/d0/30d7d035-fd8c-fe03-1624-b18482c95f0e/4b773e07-797a-4074-9a53-91f79702cc0a.png/170x170bb.png",
      "genre": "Government",
      "genre_id": "1511",
      "url": "https://podcasts.apple.com/de/podcast/something-different-with-john-and-sarah/id1896884336?uo=2"
    },
    {
      "rank": 167,
      "apple_id": "1554543488",
      "name": "Echt. Mehr. Bayern. ‚Let’s Talk Innenpolitik‘ mit Joachim Herrmann",
      "artist": "Bayerisches Staatsministerium des Innern, für Sport und Integration",
      "artwork": "https://is1-ssl.mzstatic.com/image/thumb/Podcasts211/v4/72/7a/f4/727af4a8-784f-d6c7-e2a5-3059bfe6e557/mza_8123711189761987313.png/170x170bb.png",
      "genre": "Government",
      "genre_id": "1511",
      "url": "https://podcasts.apple.com/de/podcast/echt-mehr-bayern-lets-talk-innenpolitik-mit-joachim/id1554543488?uo=2"
    },
    {
      "rank": 168,
      "apple_id": "1441555344",
      "name": "BUND Naturschutz Radio",
      "artist": "BUND Naturschutz - Kreisgruppe München",
      "artwork": "https://is1-ssl.mzstatic.com/image/thumb/Podcasts123/v4/53/a3/c3/53a3c359-74fc-56eb-66f3-9a113892c20e/mza_2314061920872083265.jpg/170x170bb.png",
      "genre": "Government",
      "genre_id": "1511",
      "url": "https://podcasts.apple.com/de/podcast/bund-naturschutz-radio/id1441555344?uo=2"
    },
    {
      "rank": 169,
      "apple_id": "1586804082",
      "name": "Proces Verbaal",
      "artist": "Raad voor de rechtspraak",
      "artwork": "https://is1-ssl.mzstatic.com/image/thumb/Podcasts115/v4/d8/61/6e/d8616e76-4a8a-3309-12bf-fb339e8b0bdd/mza_11142839751418964850.jpg/170x170bb.png",
      "genre": "Government",
      "genre_id": "1511",
      "url": "https://podcasts.apple.com/de/podcast/proces-verbaal/id1586804082?uo=2"
    },
    {
      "rank": 170,
      "apple_id": "1697417703",
      "name": "Un Mundo de Sensaciones",
      "artist": "Futurock",
      "artwork": "https://is1-ssl.mzstatic.com/image/thumb/Podcasts116/v4/ac/ba/b4/acbab48a-fbdf-53ca-67ea-c1c8ded4e5a6/mza_46235646533496143.jpg/170x170bb.png",
      "genre": "Government",
      "genre_id": "1511",
      "url": "https://podcasts.apple.com/de/podcast/un-mundo-de-sensaciones/id1697417703?uo=2"
    },
    {
      "rank": 171,
      "apple_id": "1773334458",
      "name": "The Fascism Barometer",
      "artist": "Ejeris Dixon",
      "artwork": "https://is1-ssl.mzstatic.com/image/thumb/Podcasts211/v4/10/74/ad/1074add5-6416-3bf9-b6a8-a806300a2cdc/mza_12464793351373951503.jpg/170x170bb.png",
      "genre": "Government",
      "genre_id": "1511",
      "url": "https://podcasts.apple.com/de/podcast/the-fascism-barometer/id1773334458?uo=2"
    },
    {
      "rank": 172,
      "apple_id": "1571046531",
      "name": "Stories of Special Forces Operators",
      "artist": "Circle Of Insight Productions",
      "artwork": "https://is1-ssl.mzstatic.com/image/thumb/Podcasts115/v4/37/f9/56/37f956a5-4119-6b59-19fa-9d4e4deafb07/mza_80783134293329420.jpg/170x170bb.png",
      "genre": "Government",
      "genre_id": "1511",
      "url": "https://podcasts.apple.com/de/podcast/stories-of-special-forces-operators/id1571046531?uo=2"
    },
    {
      "rank": 173,
      "apple_id": "1802722241",
      "name": "The Find Out Podcast",
      "artist": "Find Out Media & Studio71",
      "artwork": "https://is1-ssl.mzstatic.com/image/thumb/Podcasts211/v4/a7/56/a3/a756a3f0-1223-2109-8e0b-cbee50f71a90/mza_8669726937084340455.jpg/170x170bb.png",
      "genre": "Government",
      "genre_id": "1511",
      "url": "https://podcasts.apple.com/de/podcast/the-find-out-podcast/id1802722241?uo=2"
    },
    {
      "rank": 174,
      "apple_id": "1533272025",
      "name": "Democracy in Question?",
      "artist": "Albert Hirschman Centre on Democracy",
      "artwork": "https://is1-ssl.mzstatic.com/image/thumb/Podcasts211/v4/df/25/96/df2596bf-4bd0-bca3-b9f6-07c10696573e/mza_2650328718660714706.jpg/170x170bb.png",
      "genre": "Government",
      "genre_id": "1511",
      "url": "https://podcasts.apple.com/de/podcast/democracy-in-question/id1533272025?uo=2"
    },
    {
      "rank": 175,
      "apple_id": "1890489548",
      "name": "Grünschnäbel – der progressive Podcast!",
      "artist": "Grüne Jugend Werra-Meißner",
      "artwork": "https://is1-ssl.mzstatic.com/image/thumb/Podcasts211/v4/bb/72/9a/bb729a75-be8a-3f80-a0dd-e464922cac18/mza_11959953058379672038.jpg/170x170bb.png",
      "genre": "Government",
      "genre_id": "1511",
      "url": "https://podcasts.apple.com/de/podcast/gr%C3%BCnschn%C3%A4bel-der-progressive-podcast/id1890489548?uo=2"
    },
    {
      "rank": 176,
      "apple_id": "1896901597",
      "name": "Checks & Balances",
      "artist": "Checks & Balances",
      "artwork": "https://is1-ssl.mzstatic.com/image/thumb/Podcasts221/v4/38/5b/f4/385bf4a8-ea88-cd76-8841-581d60d34c5e/mza_8403339447417408261.jpg/170x170bb.png",
      "genre": "Government",
      "genre_id": "1511",
      "url": "https://podcasts.apple.com/de/podcast/checks-balances/id1896901597?uo=2"
    },
    {
      "rank": 177,
      "apple_id": "1507485854",
      "name": "Streaming Water",
      "artist": "Blair Corning",
      "artwork": "https://is1-ssl.mzstatic.com/image/thumb/Podcasts126/v4/a2/a4/71/a2a47129-3b7b-98ba-e76c-87a002d973eb/mza_7160736536807734049.jpg/170x170bb.png",
      "genre": "Government",
      "genre_id": "1511",
      "url": "https://podcasts.apple.com/de/podcast/streaming-water/id1507485854?uo=2"
    },
    {
      "rank": 178,
      "apple_id": "1446784509",
      "name": "Donnybrook",
      "artist": "Nine PBS",
      "artwork": "https://is1-ssl.mzstatic.com/image/thumb/Podcasts221/v4/ef/b6/09/efb60953-89fb-9f90-736c-93d78e31af7b/mza_10324928483889003104.jpg/170x170bb.png",
      "genre": "Government",
      "genre_id": "1511",
      "url": "https://podcasts.apple.com/de/podcast/donnybrook/id1446784509?uo=2"
    },
    {
      "rank": 179,
      "apple_id": "1368621724",
      "name": "A Better Peace: The War Room Podcast",
      "artist": "A Better Peace: The War Room Podcast",
      "artwork": "https://is1-ssl.mzstatic.com/image/thumb/Podcasts221/v4/f8/c4/48/f8c4482b-792d-4053-051d-4d59f3bc4b77/mza_6228490944601196407.png/170x170bb.png",
      "genre": "Government",
      "genre_id": "1511",
      "url": "https://podcasts.apple.com/de/podcast/a-better-peace-the-war-room-podcast/id1368621724?uo=2"
    },
    {
      "rank": 180,
      "apple_id": "1869594351",
      "name": "L'ordre du monde",
      "artist": "BFM Business",
      "artwork": "https://is1-ssl.mzstatic.com/image/thumb/Podcasts211/v4/41/90/17/41901761-5e3a-3e17-0087-2d1c0e243761/mza_3448785113284408863.jpg/170x170bb.png",
      "genre": "Government",
      "genre_id": "1511",
      "url": "https://podcasts.apple.com/de/podcast/lordre-du-monde/id1869594351?uo=2"
    },
    {
      "rank": 181,
      "apple_id": "1694514515",
      "name": "Stadt Wien Podcast",
      "artist": "Stadt Wien",
      "artwork": "https://is1-ssl.mzstatic.com/image/thumb/Podcasts211/v4/15/06/aa/1506aa2b-8678-6877-524f-5b77e0bf1610/mza_17861205037271538706.jpg/170x170bb.png",
      "genre": "Government",
      "genre_id": "1511",
      "url": "https://podcasts.apple.com/de/podcast/stadt-wien-podcast/id1694514515?uo=2"
    },
    {
      "rank": 182,
      "apple_id": "1204903121",
      "name": "Brexit: A Guide for the Perplexed",
      "artist": "BBC Radio 4",
      "artwork": "https://is1-ssl.mzstatic.com/image/thumb/Podcasts125/v4/23/05/d8/2305d882-2889-cfcf-9eff-aacff9074b38/mza_14674196551282950956.jpg/170x170bb.png",
      "genre": "Government",
      "genre_id": "1511",
      "url": "https://podcasts.apple.com/de/podcast/brexit-a-guide-for-the-perplexed/id1204903121?uo=2"
    },
    {
      "rank": 183,
      "apple_id": "1389951701",
      "name": "The Impossible State",
      "artist": "CSIS | Center for Strategic and International Studies",
      "artwork": "https://is1-ssl.mzstatic.com/image/thumb/Podcasts211/v4/c9/81/a8/c981a87a-d8f9-55a7-3af3-4e183cd669a7/mza_7429283162148512087.jpg/170x170bb.png",
      "genre": "Government",
      "genre_id": "1511",
      "url": "https://podcasts.apple.com/de/podcast/the-impossible-state/id1389951701?uo=2"
    },
    {
      "rank": 184,
      "apple_id": "1501674361",
      "name": "KenFM: Positionen - Politik verstehen",
      "artist": "KenFM",
      "artwork": "https://is1-ssl.mzstatic.com/image/thumb/Podcasts125/v4/65/f8/c8/65f8c876-ad66-d7ea-e163-c3ea09dead0c/mza_14822300662430493308.jpeg/170x170bb.png",
      "genre": "Government",
      "genre_id": "1511",
      "url": "https://podcasts.apple.com/de/podcast/kenfm-positionen-politik-verstehen/id1501674361?uo=2"
    },
    {
      "rank": 185,
      "apple_id": "1860682415",
      "name": "The Lawfare Podcast: Patreon Edition",
      "artist": "The Lawfare Institute",
      "artwork": "https://is1-ssl.mzstatic.com/image/thumb/Podcasts211/v4/b1/3c/23/b13c2361-cb43-742b-f85d-6fc7797945b4/mza_3067999191585511627.jpeg/170x170bb.png",
      "genre": "Government",
      "genre_id": "1511",
      "url": "https://podcasts.apple.com/de/podcast/the-lawfare-podcast-patreon-edition/id1860682415?uo=2"
    },
    {
      "rank": 186,
      "apple_id": "1636535086",
      "name": "Taiwan Salon",
      "artist": "Global Taiwan Institute",
      "artwork": "https://is1-ssl.mzstatic.com/image/thumb/Podcasts126/v4/f1/98/ce/f198cebb-a09c-55c5-6655-06ea8b60e12c/mza_8138205139612659219.jpg/170x170bb.png",
      "genre": "Government",
      "genre_id": "1511",
      "url": "https://podcasts.apple.com/de/podcast/taiwan-salon/id1636535086?uo=2"
    },
    {
      "rank": 187,
      "apple_id": "1008204278",
      "name": "Alzheimer's Society Podcast",
      "artist": "Alzheimer's Society",
      "artwork": "https://is1-ssl.mzstatic.com/image/thumb/Podcasts62/v4/f4/06/f3/f406f3a1-90a3-3067-98ac-2b296c2fde41/mza_8770615357759989329.jpg/170x170bb.png",
      "genre": "Government",
      "genre_id": "1511",
      "url": "https://podcasts.apple.com/de/podcast/alzheimers-society-podcast/id1008204278?uo=2"
    },
    {
      "rank": 188,
      "apple_id": "1896785800",
      "name": "Zickler und Ketzer - leider ehrlich!",
      "artist": "Zickler und Ketzer",
      "artwork": "https://is1-ssl.mzstatic.com/image/thumb/Podcasts211/v4/ca/56/b2/ca56b296-c879-efc1-bec5-097b2a55cb2c/mza_16992406309942680629.jpg/170x170bb.png",
      "genre": "Government",
      "genre_id": "1511",
      "url": "https://podcasts.apple.com/de/podcast/zickler-und-ketzer-leider-ehrlich/id1896785800?uo=2"
    },
    {
      "rank": 189,
      "apple_id": "1577996421",
      "name": "Entitled",
      "artist": "University of Chicago Podcast Network",
      "artwork": "https://is1-ssl.mzstatic.com/image/thumb/Podcasts211/v4/9f/d4/47/9fd447bc-8361-8390-923d-65bac22f344b/mza_17510990411975508707.jpg/170x170bb.png",
      "genre": "Government",
      "genre_id": "1511",
      "url": "https://podcasts.apple.com/de/podcast/entitled/id1577996421?uo=2"
    },
    {
      "rank": 190,
      "apple_id": "1739339252",
      "name": "MASZ & Moritz",
      "artist": "FDP",
      "artwork": "https://is1-ssl.mzstatic.com/image/thumb/Podcasts211/v4/35/a9/f4/35a9f493-8690-91ae-b715-f81f88031700/mza_5349218215408569274.jpeg/170x170bb.png",
      "genre": "Government",
      "genre_id": "1511",
      "url": "https://podcasts.apple.com/de/podcast/masz-moritz/id1739339252?uo=2"
    },
    {
      "rank": 191,
      "apple_id": "1476872871",
      "name": "35 West",
      "artist": "Center for Strategic and International Studies",
      "artwork": "https://is1-ssl.mzstatic.com/image/thumb/Podcasts221/v4/a2/9d/ea/a29deaf1-7a35-d3f1-85ce-1a5926745b76/mza_4776212308627690980.jpg/170x170bb.png",
      "genre": "Government",
      "genre_id": "1511",
      "url": "https://podcasts.apple.com/de/podcast/35-west/id1476872871?uo=2"
    },
    {
      "rank": 192,
      "apple_id": "1740765238",
      "name": "Der Friedberg Podcast",
      "artist": "Stadt Friedberg",
      "artwork": "https://is1-ssl.mzstatic.com/image/thumb/Podcasts221/v4/b0/a3/a7/b0a3a7fd-153c-d339-e069-5e81ef81fa8a/mza_10072553814379609089.jpg/170x170bb.png",
      "genre": "Government",
      "genre_id": "1511",
      "url": "https://podcasts.apple.com/de/podcast/der-friedberg-podcast/id1740765238?uo=2"
    },
    {
      "rank": 193,
      "apple_id": "1588665474",
      "name": "Palavras do Brasil",
      "artist": "Agência Timbres",
      "artwork": "https://is1-ssl.mzstatic.com/image/thumb/Podcasts125/v4/c9/80/56/c9805665-60ce-a77e-c815-ecd1b5386134/mza_6788167053123245080.jpg/170x170bb.png",
      "genre": "Government",
      "genre_id": "1511",
      "url": "https://podcasts.apple.com/de/podcast/palavras-do-brasil/id1588665474?uo=2"
    },
    {
      "rank": 194,
      "apple_id": "1557214082",
      "name": "Food for Europe",
      "artist": "European Commission, Directorate General for Agriculture and Rural Development",
      "artwork": "https://is1-ssl.mzstatic.com/image/thumb/Podcasts124/v4/f0/6b/4b/f06b4b0f-4b56-aa9a-a594-7bbf3e4aed02/mza_14520128520544362303.jpg/170x170bb.png",
      "genre": "Government",
      "genre_id": "1511",
      "url": "https://podcasts.apple.com/de/podcast/food-for-europe/id1557214082?uo=2"
    },
    {
      "rank": 195,
      "apple_id": "1572098766",
      "name": "Podcast JOSEF STALIN",
      "artist": "Ana Clara Lanutte",
      "artwork": "https://is1-ssl.mzstatic.com/image/thumb/Podcasts115/v4/d5/ce/b3/d5ceb379-ec79-16e4-44b9-4045e0d21c96/mza_8725324453844229876.jpg/170x170bb.png",
      "genre": "Government",
      "genre_id": "1511",
      "url": "https://podcasts.apple.com/de/podcast/podcast-josef-stalin/id1572098766?uo=2"
    },
    {
      "rank": 196,
      "apple_id": "1800500845",
      "name": "Stunk. Palmer bringt die Welt in Ordnung",
      "artist": "SWR, Sandra Kolnik, Alexandra Müller",
      "artwork": "https://is1-ssl.mzstatic.com/image/thumb/Podcasts221/v4/f0/75/e7/f075e75f-0bb3-749d-c030-6a78a35aa922/mza_14778901715890104555.jpg/170x170bb.png",
      "genre": "Government",
      "genre_id": "1511",
      "url": "https://podcasts.apple.com/de/podcast/stunk-palmer-bringt-die-welt-in-ordnung/id1800500845?uo=2"
    },
    {
      "rank": 197,
      "apple_id": "1500237436",
      "name": "Lignes de défense",
      "artist": "RFI",
      "artwork": "https://is1-ssl.mzstatic.com/image/thumb/Podcasts112/v4/04/94/7c/04947c30-8a5d-8137-cb83-f39ed010ccc8/mza_7377357258723841252.jpg/170x170bb.png",
      "genre": "Government",
      "genre_id": "1511",
      "url": "https://podcasts.apple.com/de/podcast/lignes-de-d%C3%A9fense/id1500237436?uo=2"
    },
    {
      "rank": 198,
      "apple_id": "1652159219",
      "name": "Better Politics Podcast",
      "artist": "Better Politics Foundation",
      "artwork": "https://is1-ssl.mzstatic.com/image/thumb/Podcasts221/v4/15/b8/a1/15b8a138-a09e-94f9-d808-c8e694e064cd/mza_11703767240420483154.jpg/170x170bb.png",
      "genre": "Government",
      "genre_id": "1511",
      "url": "https://podcasts.apple.com/de/podcast/better-politics-podcast/id1652159219?uo=2"
    },
    {
      "rank": 199,
      "apple_id": "1528218862",
      "name": "HIER\\GEBLIEBEN",
      "artist": "Kölner Flüchtlingsrat e.V.",
      "artwork": "https://is1-ssl.mzstatic.com/image/thumb/Podcasts126/v4/b1/a8/ca/b1a8ca2f-7ef6-b538-ab5d-2d2c1140869c/mza_2987347986929185467.jpg/170x170bb.png",
      "genre": "Government",
      "genre_id": "1511",
      "url": "https://podcasts.apple.com/de/podcast/hier-geblieben/id1528218862?uo=2"
    },
    {
      "rank": 200,
      "apple_id": "1823289204",
      "name": "Zohran Mamdani - Biography Flash",
      "artist": "Inception Point AI",
      "artwork": "https://is1-ssl.mzstatic.com/image/thumb/Podcasts221/v4/24/df/12/24df129b-5299-2b7d-57c3-ac8332cb12c8/mza_5020062164533083991.jpg/170x170bb.png",
      "genre": "Government",
      "genre_id": "1511",
      "url": "https://podcasts.apple.com/de/podcast/zohran-mamdani-biography-flash/id1823289204?uo=2"
    }
  ]
}