{
    "platform": "spotify",
    "country": "mx",
    "genre": "Education",
    "slug": "education",
    "fetched_at": "2026-07-01T04:44:53Z",
    "count": 50,
    "shows": [
        {
            "rank": 1,
            "spotify_id": "40y17ac2O4ILlp9n62PErK",
            "name": "Martha Debayle",
            "publisher": "Martha Debayle",
            "artwork": "https:\/\/i.scdn.co\/image\/ab67656300005f1f3522a340e9e872291c45a7dc",
            "rank_move": "UNCHANGED",
            "url": "https:\/\/open.spotify.com\/show\/40y17ac2O4ILlp9n62PErK"
        },
        {
            "rank": 2,
            "spotify_id": "2rvGjOgeyQTtl5ZgXzUXoQ",
            "name": "Estoicismo Filosofia",
            "publisher": "Estoicismo Filosofia",
            "artwork": "https:\/\/i.scdn.co\/image\/ab67656300005f1fca838f294e8cbd41903db624",
            "rank_move": "UNCHANGED",
            "url": "https:\/\/open.spotify.com\/show\/2rvGjOgeyQTtl5ZgXzUXoQ"
        },
        {
            "rank": 3,
            "spotify_id": "5GfRxX2kl2BJVB1e7AgcDh",
            "name": "El Podcast de Marco Antonio Regil",
            "publisher": "Sonoro | Marco Antonio Regil",
            "artwork": "https:\/\/i.scdn.co\/image\/ab67656300005f1fcfc7dc9d8cbde5f1932f06a4",
            "rank_move": "UNCHANGED",
            "url": "https:\/\/open.spotify.com\/show\/5GfRxX2kl2BJVB1e7AgcDh"
        },
        {
            "rank": 4,
            "spotify_id": "0u43AimG7Ap5Xkqo5hJ5CZ",
            "name": "Meditaciones Guiadas canal Mente Consciente",
            "publisher": "Mente Consciente",
            "artwork": "https:\/\/i.scdn.co\/image\/ab67656300005f1fea232ea765832897fb1fa928",
            "rank_move": "UNCHANGED",
            "url": "https:\/\/open.spotify.com\/show\/0u43AimG7Ap5Xkqo5hJ5CZ"
        },
        {
            "rank": 5,
            "spotify_id": "1y5jFGgeRUcewEvEqcgVfy",
            "name": "Sara Romero | Mente, Conciencia y Método SOMA®",
            "publisher": "Método SOMA",
            "artwork": "https:\/\/i.scdn.co\/image\/ab67656300005f1f9b79c57f5dc35dd6469ae030",
            "rank_move": "UNCHANGED",
            "url": "https:\/\/open.spotify.com\/show\/1y5jFGgeRUcewEvEqcgVfy"
        },
        {
            "rank": 6,
            "spotify_id": "048nMXlfLoBewmcckhDoFn",
            "name": "La buena platica",
            "publisher": "Rodrigo Macías",
            "artwork": "https:\/\/i.scdn.co\/image\/ab67656300005f1f5b621d9a6fef33c6b2cfbaad",
            "rank_move": "UNCHANGED",
            "url": "https:\/\/open.spotify.com\/show\/048nMXlfLoBewmcckhDoFn"
        },
        {
            "rank": 7,
            "spotify_id": "4lZFqpHxdc9sCourU6AMAf",
            "name": "Espíritu Estoico",
            "publisher": "Espíritu Estoico",
            "artwork": "https:\/\/i.scdn.co\/image\/ab67656300005f1f5ae38758563d5a022e02de69",
            "rank_move": "UNCHANGED",
            "url": "https:\/\/open.spotify.com\/show\/4lZFqpHxdc9sCourU6AMAf"
        },
        {
            "rank": 8,
            "spotify_id": "4hz0jLXfWc9jzCsAybaSgI",
            "name": "Dr. Mario Alonso Puig",
            "publisher": "Mario Alonso Puig",
            "artwork": "https:\/\/i.scdn.co\/image\/ab67656300005f1fc5acdc689b866d7788f10202",
            "rank_move": "UP",
            "url": "https:\/\/open.spotify.com\/show\/4hz0jLXfWc9jzCsAybaSgI"
        },
        {
            "rank": 9,
            "spotify_id": "53bnc3AHyqknK2JMAHo9br",
            "name": "LA MAGIA DEL CAOS con Aislinn Derbez",
            "publisher": "Aislinn Derbez",
            "artwork": "https:\/\/i.scdn.co\/image\/ab67656300005f1fe7818340ce48aa525a578871",
            "rank_move": "UNCHANGED",
            "url": "https:\/\/open.spotify.com\/show\/53bnc3AHyqknK2JMAHo9br"
        },
        {
            "rank": 10,
            "spotify_id": "7ncyJYUUGTOJKgRkMrdep3",
            "name": "Aprende a Tener Éxito",
            "publisher": "MGN",
            "artwork": "https:\/\/i.scdn.co\/image\/ab67656300005f1f967c10dc30fdc429bdef2428",
            "rank_move": "DOWN",
            "url": "https:\/\/open.spotify.com\/show\/7ncyJYUUGTOJKgRkMrdep3"
        },
        {
            "rank": 11,
            "spotify_id": "3j8c7Q59ilDYuJeIme0M6X",
            "name": "Motivación para la vida",
            "publisher": "Chispa Motivation Español",
            "artwork": "https:\/\/i.scdn.co\/image\/ab67656300005f1f1f8d98b679f828f62c052127",
            "rank_move": "UNCHANGED",
            "url": "https:\/\/open.spotify.com\/show\/3j8c7Q59ilDYuJeIme0M6X"
        },
        {
            "rank": 12,
            "spotify_id": "2aRde7TmqmBrrSYZ62RYUg",
            "name": "Nayo Escobar Podcast",
            "publisher": "Nayo Escobar",
            "artwork": "https:\/\/i.scdn.co\/image\/ab67656300005f1f51567624fe6f47050f3d47bd",
            "rank_move": "UP",
            "url": "https:\/\/open.spotify.com\/show\/2aRde7TmqmBrrSYZ62RYUg"
        },
        {
            "rank": 13,
            "spotify_id": "1nXFirxOfpjJ6E9URdMbuy",
            "name": "La Verdad Cuesta",
            "publisher": "Javier Cuesta",
            "artwork": "https:\/\/i.scdn.co\/image\/ab67656300005f1f2ea674a377daef9738ab490e",
            "rank_move": "DOWN",
            "url": "https:\/\/open.spotify.com\/show\/1nXFirxOfpjJ6E9URdMbuy"
        },
        {
            "rank": 14,
            "spotify_id": "75qxqKlaKdJKBNnt4Tb0R2",
            "name": "Diego Ruzzarin",
            "publisher": "Diego Ruzzarin",
            "artwork": "https:\/\/i.scdn.co\/image\/ab67656300005f1f458208934f1a5c238be18131",
            "rank_move": "UP",
            "url": "https:\/\/open.spotify.com\/show\/75qxqKlaKdJKBNnt4Tb0R2"
        },
        {
            "rank": 15,
            "spotify_id": "3pdTvXmezybrc6if0CQBOr",
            "name": "EL TEMACH PODCAST",
            "publisher": "El Temach",
            "artwork": "https:\/\/i.scdn.co\/image\/ab67656300005f1f6ff78a07a545142c09f31c53",
            "rank_move": "DOWN",
            "url": "https:\/\/open.spotify.com\/show\/3pdTvXmezybrc6if0CQBOr"
        },
        {
            "rank": 16,
            "spotify_id": "7MAGHGjX5mMVj7mrOASpNq",
            "name": "La Verdad del Ser",
            "publisher": "Maria Celeste",
            "artwork": "https:\/\/i.scdn.co\/image\/ab67656300005f1f9b6cc649eafa0c187247e5bc",
            "rank_move": "UNCHANGED",
            "url": "https:\/\/open.spotify.com\/show\/7MAGHGjX5mMVj7mrOASpNq"
        },
        {
            "rank": 17,
            "spotify_id": "5T6nge86sgwXW0TnpNoLTY",
            "name": "Tu Desarrollo Personal",
            "publisher": "Mente_Presocratica",
            "artwork": "https:\/\/i.scdn.co\/image\/ab67656300005f1ff65ba1309f89e91fcbff54c0",
            "rank_move": "UNCHANGED",
            "url": "https:\/\/open.spotify.com\/show\/5T6nge86sgwXW0TnpNoLTY"
        },
        {
            "rank": 18,
            "spotify_id": "2sTV4YRhKMyZtweTJyx2hD",
            "name": "EL TEMACH - MOTIVACIÓN para el GYM 💪🏼🏋🏻‍♀🔱 💥MODO GUERRA💥",
            "publisher": "El Compa Alex",
            "artwork": "https:\/\/i.scdn.co\/image\/ab67656300005f1f63fa5488298554af3bdf1ced",
            "rank_move": "UNCHANGED",
            "url": "https:\/\/open.spotify.com\/show\/2sTV4YRhKMyZtweTJyx2hD"
        },
        {
            "rank": 19,
            "spotify_id": "3UtuoTVTzBUQqIblcSMv6p",
            "name": "Estoicismo para Ganadores",
            "publisher": "Estoicismo Para Ganadores",
            "artwork": "https:\/\/i.scdn.co\/image\/ab67656300005f1fa8b5ff1ed4cd7ee88d55ffcc",
            "rank_move": "UNCHANGED",
            "url": "https:\/\/open.spotify.com\/show\/3UtuoTVTzBUQqIblcSMv6p"
        },
        {
            "rank": 20,
            "spotify_id": "07rXxtOlzNI0NuB8vpAgvE",
            "name": "BBVA Aprendemos juntos",
            "publisher": "BBVA Podcast",
            "artwork": "https:\/\/i.scdn.co\/image\/ab67656300005f1fa607dfb82ca7b301e4bfd7a3",
            "rank_move": "UNCHANGED",
            "url": "https:\/\/open.spotify.com\/show\/07rXxtOlzNI0NuB8vpAgvE"
        },
        {
            "rank": 21,
            "spotify_id": "1KRwhKl60iMj3r9QH5fTnf",
            "name": "Inglés desde cero",
            "publisher": "Daniel Barbour & Stephen Bain",
            "artwork": "https:\/\/i.scdn.co\/image\/ab67656300005f1f5e98b573f37cd676e453117e",
            "rank_move": "UNCHANGED",
            "url": "https:\/\/open.spotify.com\/show\/1KRwhKl60iMj3r9QH5fTnf"
        },
        {
            "rank": 22,
            "spotify_id": "3GRJb6bwpKEbOOG7QFjRqS",
            "name": "Listening Time: English Practice",
            "publisher": "Sonoro |  Conner Pe",
            "artwork": "https:\/\/i.scdn.co\/image\/ab67656300005f1f348fe426b8a23623effb434b",
            "rank_move": "UNCHANGED",
            "url": "https:\/\/open.spotify.com\/show\/3GRJb6bwpKEbOOG7QFjRqS"
        },
        {
            "rank": 23,
            "spotify_id": "7kz871KX6zImeIPeAsofFQ",
            "name": "Vida Plena ",
            "publisher": "RaulNetworker",
            "artwork": "https:\/\/i.scdn.co\/image\/ab67656300005f1f9267c2ab94a38518b373c304",
            "rank_move": "UNCHANGED",
            "url": "https:\/\/open.spotify.com\/show\/7kz871KX6zImeIPeAsofFQ"
        },
        {
            "rank": 24,
            "spotify_id": "3iCbVRRtTh2ALsKOFoImSp",
            "name": "FIESTA PARA DAÑADOS",
            "publisher": "ELÁN",
            "artwork": "https:\/\/i.scdn.co\/image\/ab67656300005f1fd6b5358ebfbab406bd4ce3af",
            "rank_move": "UNCHANGED",
            "url": "https:\/\/open.spotify.com\/show\/3iCbVRRtTh2ALsKOFoImSp"
        },
        {
            "rank": 25,
            "spotify_id": "0WEqNybNBwZPZTM1V1iG2i",
            "name": "Black Mango Podcast",
            "publisher": "Black Mango",
            "artwork": "https:\/\/i.scdn.co\/image\/ab67656300005f1f72bc5a3aa2803a9c1702078e",
            "rank_move": "UP",
            "url": "https:\/\/open.spotify.com\/show\/0WEqNybNBwZPZTM1V1iG2i"
        },
        {
            "rank": 26,
            "spotify_id": "7DyGTThUPzz8dlQPL6uVtF",
            "name": "Esquincast",
            "publisher": "Antonio Esquinca ",
            "artwork": "https:\/\/i.scdn.co\/image\/ab67656300005f1fd75da9cc483563530a0d17d8",
            "rank_move": "UP",
            "url": "https:\/\/open.spotify.com\/show\/7DyGTThUPzz8dlQPL6uVtF"
        },
        {
            "rank": 27,
            "spotify_id": "1BbjMM53lCFrde8WFy2qAv",
            "name": "Mente en Pausa",
            "publisher": "Psic. Hannah Anda",
            "artwork": "https:\/\/i.scdn.co\/image\/ab67656300005f1f753a07d510ae2fe35ac253be",
            "rank_move": "DOWN",
            "url": "https:\/\/open.spotify.com\/show\/1BbjMM53lCFrde8WFy2qAv"
        },
        {
            "rank": 28,
            "spotify_id": "77di3WAQNvmdwGDU2oFLJF",
            "name": "Librería Prohibida",
            "publisher": "Tilka5",
            "artwork": "https:\/\/i.scdn.co\/image\/ab67656300005f1ffa94dfd60ccca3585d5a9450",
            "rank_move": "UNCHANGED",
            "url": "https:\/\/open.spotify.com\/show\/77di3WAQNvmdwGDU2oFLJF"
        },
        {
            "rank": 29,
            "spotify_id": "0XE08Cr5LbpcozQr8nyLNc",
            "name": "Ojalá lo hubiera sabido antes",
            "publisher": "Álex Rovira",
            "artwork": "https:\/\/i.scdn.co\/image\/ab67656300005f1f7fe58cb027d4cbf0e42354ff",
            "rank_move": "UP",
            "url": "https:\/\/open.spotify.com\/show\/0XE08Cr5LbpcozQr8nyLNc"
        },
        {
            "rank": 30,
            "spotify_id": "7vz4RYsD5MulTCrcH478t1",
            "name": "The Mel Robbins Podcast",
            "publisher": "Mel Robbins",
            "artwork": "https:\/\/i.scdn.co\/image\/ab67656300005f1f464250c491dc86ec4316431f",
            "rank_move": "DOWN",
            "url": "https:\/\/open.spotify.com\/show\/7vz4RYsD5MulTCrcH478t1"
        },
        {
            "rank": 31,
            "spotify_id": "6mgmbgJhvLinMYv0nWIpoa",
            "name": "Ingeniería Astral",
            "publisher": "Tilka5",
            "artwork": "https:\/\/i.scdn.co\/image\/ab67656300005f1f9c17dfc73a438e8d78948cd7",
            "rank_move": "UP",
            "url": "https:\/\/open.spotify.com\/show\/6mgmbgJhvLinMYv0nWIpoa"
        },
        {
            "rank": 32,
            "spotify_id": "6ELbafj6q90rrdfy1HqpQj",
            "name": "Los EnVivos de El Temach",
            "publisher": "El Podcaster",
            "artwork": "https:\/\/i.scdn.co\/image\/ab67656300005f1fa94b29c75d6189f23a919035",
            "rank_move": "DOWN",
            "url": "https:\/\/open.spotify.com\/show\/6ELbafj6q90rrdfy1HqpQj"
        },
        {
            "rank": 33,
            "spotify_id": "0huUiLX2Om4dyunNVtPVMd",
            "name": "Aprendemos Juntos México",
            "publisher": "BBVA Podcast México",
            "artwork": "https:\/\/i.scdn.co\/image\/ab67656300005f1ffcfdaaf48c57799bdc4ef3fb",
            "rank_move": "UNCHANGED",
            "url": "https:\/\/open.spotify.com\/show\/0huUiLX2Om4dyunNVtPVMd"
        },
        {
            "rank": 34,
            "spotify_id": "1oKeAqoc8D1K1r0UU9yKY9",
            "name": "Sinceramente por Meche Barragán | @meche_barragan",
            "publisher": "Meche Barragan",
            "artwork": "https:\/\/i.scdn.co\/image\/ab67656300005f1f704ca93157384039bc4ca972",
            "rank_move": "UP",
            "url": "https:\/\/open.spotify.com\/show\/1oKeAqoc8D1K1r0UU9yKY9"
        },
        {
            "rank": 35,
            "spotify_id": "3KdWOLIY500u1P6w2CHLfT",
            "name": "Ser grande pensando grande",
            "publisher": "oscar mojica",
            "artwork": "https:\/\/i.scdn.co\/image\/ab67656300005f1f78a9c2273f38844a7b46131e",
            "rank_move": "UP",
            "url": "https:\/\/open.spotify.com\/show\/3KdWOLIY500u1P6w2CHLfT"
        },
        {
            "rank": 36,
            "spotify_id": "4oWZjj7vr7nSpFym7qTY47",
            "name": "La Bienvenida",
            "publisher": "Spotify Studios",
            "artwork": "https:\/\/i.scdn.co\/image\/ab67656300005f1fe9b9b87e32da36008344cccf",
            "rank_move": "DOWN",
            "url": "https:\/\/open.spotify.com\/show\/4oWZjj7vr7nSpFym7qTY47"
        },
        {
            "rank": 37,
            "spotify_id": "0RjrXVjw3FhNlO7saEPoSF",
            "name": "Relatos en inglés con Duolingo",
            "publisher": "Duolingo",
            "artwork": "https:\/\/i.scdn.co\/image\/ab67656300005f1f564d348e2fadeebb16487edf",
            "rank_move": "UP",
            "url": "https:\/\/open.spotify.com\/show\/0RjrXVjw3FhNlO7saEPoSF"
        },
        {
            "rank": 38,
            "spotify_id": "2Rldfy8hmjP3fnLOgdlpEx",
            "name": "LIBRE&LOCA",
            "publisher": "Roberta Woodworth",
            "artwork": "https:\/\/i.scdn.co\/image\/ab67656300005f1fe763f97cf538afd66bf57eb1",
            "rank_move": "UP",
            "url": "https:\/\/open.spotify.com\/show\/2Rldfy8hmjP3fnLOgdlpEx"
        },
        {
            "rank": 39,
            "spotify_id": "5T304jbdRqmKp9Y2rHYiMu",
            "name": "Aprender A Amar",
            "publisher": "Leonardo Valeriano Macuri",
            "artwork": "https:\/\/i.scdn.co\/image\/ab67656300005f1f62035b3fc62665210a259bc9",
            "rank_move": "UP",
            "url": "https:\/\/open.spotify.com\/show\/5T304jbdRqmKp9Y2rHYiMu"
        },
        {
            "rank": 40,
            "spotify_id": "0g4uLMaKUrlXkGgwfVSAsC",
            "name": "Ticket Dorado by Isa Osorio",
            "publisher": "Isa Osorio",
            "artwork": "https:\/\/i.scdn.co\/image\/ab67656300005f1fc61552a1839f649a37170e70",
            "rank_move": "DOWN",
            "url": "https:\/\/open.spotify.com\/show\/0g4uLMaKUrlXkGgwfVSAsC"
        },
        {
            "rank": 41,
            "spotify_id": "6qXldSz1Ulq1Nvj2JK5kSR",
            "name": "All Ears English Podcast",
            "publisher": "Lindsay McMahon and Michelle Kaplan",
            "artwork": "https:\/\/i.scdn.co\/image\/ab67656300005f1f804de108d0da89482a1b84aa",
            "rank_move": "UNCHANGED",
            "url": "https:\/\/open.spotify.com\/show\/6qXldSz1Ulq1Nvj2JK5kSR"
        },
        {
            "rank": 42,
            "spotify_id": "5jfQ2gIpY8wlt8pxH7eq6d",
            "name": "El arte de agradecer ",
            "publisher": "Biguis",
            "artwork": "https:\/\/i.scdn.co\/image\/ab67656300005f1fdc8f406688d095072c8183ba",
            "rank_move": "UP",
            "url": "https:\/\/open.spotify.com\/show\/5jfQ2gIpY8wlt8pxH7eq6d"
        },
        {
            "rank": 43,
            "spotify_id": "0tWbQgGDZRSXdDlTogta6G",
            "name": "cosas que no sabias",
            "publisher": "angel cano",
            "artwork": "https:\/\/i.scdn.co\/image\/ab67656300005f1fe18baa731a4d5adabaa784ca",
            "rank_move": "UNCHANGED",
            "url": "https:\/\/open.spotify.com\/show\/0tWbQgGDZRSXdDlTogta6G"
        },
        {
            "rank": 44,
            "spotify_id": "4NpnCh4cn39NstAeRgN5si",
            "name": "Leo English Podcast",
            "publisher": "Leo English Podcast",
            "artwork": "https:\/\/i.scdn.co\/image\/ab67656300005f1fc2dd98d074b224f4c47faa04",
            "rank_move": "DOWN",
            "url": "https:\/\/open.spotify.com\/show\/4NpnCh4cn39NstAeRgN5si"
        },
        {
            "rank": 45,
            "spotify_id": "1PDB3EAbFkorBe2jl4Reon",
            "name": "El Arte de Incomodar",
            "publisher": "Gigi Glowz",
            "artwork": "https:\/\/i.scdn.co\/image\/ab67656300005f1fec59c2b1270ecab407d7d175",
            "rank_move": "UP",
            "url": "https:\/\/open.spotify.com\/show\/1PDB3EAbFkorBe2jl4Reon"
        },
        {
            "rank": 46,
            "spotify_id": "1MWuYCuxNlSPFl8zPtTjDt",
            "name": "HABITOS ATOMICOS",
            "publisher": "El yisus",
            "artwork": "https:\/\/i.scdn.co\/image\/ab67656300005f1fa7e85f4338563fdbf66d0d18",
            "rank_move": "UNCHANGED",
            "url": "https:\/\/open.spotify.com\/show\/1MWuYCuxNlSPFl8zPtTjDt"
        },
        {
            "rank": 47,
            "spotify_id": "3CF9ANEicXGxEROA3cOryE",
            "name": "6 Minute English",
            "publisher": "BBC Radio",
            "artwork": "https:\/\/i.scdn.co\/image\/ab67656300005f1fafe49ccbd89c819947b285b6",
            "rank_move": "DOWN",
            "url": "https:\/\/open.spotify.com\/show\/3CF9ANEicXGxEROA3cOryE"
        },
        {
            "rank": 48,
            "spotify_id": "4jduDj3h3zDS7WHorUntsq",
            "name": "Inteligencia & Gestión Emocional I Autoestima I Manifestación Realista",
            "publisher": "veraexploraycrece",
            "artwork": "https:\/\/i.scdn.co\/image\/ab67656300005f1f035c9fbb032da04cf6dadace",
            "rank_move": "UP",
            "url": "https:\/\/open.spotify.com\/show\/4jduDj3h3zDS7WHorUntsq"
        },
        {
            "rank": 49,
            "spotify_id": "5mSTZWNY3GbW2GTg4apwPu",
            "name": "A TODO SI",
            "publisher": "Stephanie Rodríguez",
            "artwork": "https:\/\/i.scdn.co\/image\/ab67656300005f1f85a7d321c9d65dd5af8f8c24",
            "rank_move": "DOWN",
            "url": "https:\/\/open.spotify.com\/show\/5mSTZWNY3GbW2GTg4apwPu"
        },
        {
            "rank": 50,
            "spotify_id": "1s4uoQY1C0IAnvHJE0rUMb",
            "name": "Seminario Fenix | Brian Tracy",
            "publisher": "matiasmartinez16",
            "artwork": "https:\/\/i.scdn.co\/image\/ab67656300005f1fa6f18915ac3f14651b843d6d",
            "rank_move": "DOWN",
            "url": "https:\/\/open.spotify.com\/show\/1s4uoQY1C0IAnvHJE0rUMb"
        }
    ]
}